omar/register.sv
module register#(
    parameter WIDTH = 32
)(
    input logic             clk,   
    input logic             rst,   
    input logic [WIDTH-1:0] in,      
    output logic [WIDTH-1:0] out

);

always_ff @(posedge clk) begin
    if(rst) out <= {WIDTH{1'b0}};
    else out <= in;
end

endmodule

Yi/mux.sv
module mux#(
    parameter WIDTH = 32
)(
    input logic             sel,   
    input logic [WIDTH-1:0] in_0,      
    input logic [WIDTH-1:0] in_1,        
    output logic [WIDTH-1:0] out

);

always_comb begin

    out = (sel ? in_1 : in_0) ;
    
end

endmodule

Yi/addconstant.sv
module addconstant#(
    parameter WIDTH = 32,
    parameter constant = 4
)(
    
    input logic [WIDTH-1:0] in,      
    output logic [WIDTH-1:0] out  

);

always_comb begin

    out = in + constant;
    
end

endmodule

omar/adder.sv
module adder#(
    parameter WIDTH = 32
)(
    
    input logic [WIDTH-1:0] a,      
    input logic [WIDTH-1:0] b,      
    output logic [WIDTH-1:0] sum    

);

always_comb begin

    sum = a + b;
    
end

endmodule

Yi/yi.sv
module yi #(
  parameter WIDTH = 32
)(
  // interface signals
  input  logic clk,
  input  logic rst,
  input  logic pcsrc,
  input  logic [WIDTH-1:0] immop,
  output logic [WIDTH-1:0] pc
);

wire [WIDTH-1:0] branch_pc; // interconnect wire
wire [WIDTH-1:0] inc_pc;    // interconnect wire
wire [WIDTH-1:0] next_pc;   // interconnect wire

adder adder (
  .a(pc),
  .b(immop),
  .sum(branch_pc)
);

addconstant addconstant(
  .in(pc),
  .out(inc_pc)
);

mux mux(
  .in_1(branch_pc),
  .in_0(inc_pc),
  .sel(pcsrc),
  .out(next_pc)
);

register pcreg(
  .clk(clk),
  .rst(rst),
  .in(next_pc),
  .out(pc)
);

endmodule

Yi/program_counter_with_all_adders_built/yi.vcd
$version Generated by VerilatedVcd $end
$date Sun Nov 20 16:30:16 2022
 $end
$timescale   1ps $end

 $scope module TOP $end
  $var wire  1 # clk $end
  $var wire 32 & immop [31:0] $end
  $var wire 32 ' pc [31:0] $end
  $var wire  1 % pcsrc $end
  $var wire  1 $ rst $end
  $scope module yi $end
   $var wire 32 + WIDTH [31:0] $end
   $var wire 32 ( branch_pc [31:0] $end
   $var wire  1 # clk $end
   $var wire 32 & immop [31:0] $end
   $var wire 32 ) inc_pc [31:0] $end
   $var wire 32 * next_pc [31:0] $end
   $var wire 32 ' pc [31:0] $end
   $var wire  1 % pcsrc $end
   $var wire  1 $ rst $end
   $scope module addconstant $end
    $var wire 32 + WIDTH [31:0] $end
    $var wire 32 , constant [31:0] $end
    $var wire 32 ' in [31:0] $end
    $var wire 32 ) out [31:0] $end
   $upscope $end
   $scope module adder $end
    $var wire 32 + WIDTH [31:0] $end
    $var wire 32 ' a [31:0] $end
    $var wire 32 & b [31:0] $end
    $var wire 32 ( sum [31:0] $end
   $upscope $end
   $scope module mux $end
    $var wire 32 + WIDTH [31:0] $end
    $var wire 32 ) in_0 [31:0] $end
    $var wire 32 ( in_1 [31:0] $end
    $var wire 32 * out [31:0] $end
    $var wire  1 % sel $end
   $upscope $end
   $scope module pcreg $end
    $var wire 32 + WIDTH [31:0] $end
    $var wire  1 # clk $end
    $var wire 32 * in [31:0] $end
    $var wire 32 ' out [31:0] $end
    $var wire  1 $ rst $end
   $upscope $end
  $upscope $end
 $upscope $end
$enddefinitions $end


#0
1#
1$
0%
b00000000000000000000000000000101 &
b00000000000000000000000000000000 '
b00000000000000000000000000000101 (
b00000000000000000000000000000100 )
b00000000000000000000000000000100 *
b00000000000000000000000000100000 +
b00000000000000000000000000000100 ,
#1
0#
#2
1#
0$
b00000000000000000000000000000100 '
b00000000000000000000000000001001 (
b00000000000000000000000000001000 )
b00000000000000000000000000001000 *
#3
0#
#4
1#
b00000000000000000000000000001000 '
b00000000000000000000000000001101 (
b00000000000000000000000000001100 )
b00000000000000000000000000001100 *
#5
0#
#6
1#
b00000000000000000000000000001100 '
b00000000000000000000000000010001 (
b00000000000000000000000000010000 )
b00000000000000000000000000010000 *
#7
0#
#8
1#
b00000000000000000000000000010000 '
b00000000000000000000000000010101 (
b00000000000000000000000000010100 )
b00000000000000000000000000010100 *
#9
0#
#10
1#
b00000000000000000000000000010100 '
b00000000000000000000000000011001 (
b00000000000000000000000000011000 )
b00000000000000000000000000011000 *
#11
0#
#12
1#
b00000000000000000000000000011000 '
b00000000000000000000000000011101 (
b00000000000000000000000000011100 )
b00000000000000000000000000011100 *
#13
0#
#14
1#
b00000000000000000000000000011100 '
b00000000000000000000000000100001 (
b00000000000000000000000000100000 )
b00000000000000000000000000100000 *
#15
0#
#16
1#
b00000000000000000000000000100000 '
b00000000000000000000000000100101 (
b00000000000000000000000000100100 )
b00000000000000000000000000100100 *
#17
0#
#18
1#
b00000000000000000000000000100100 '
b00000000000000000000000000101001 (
b00000000000000000000000000101000 )
b00000000000000000000000000101000 *
#19
0#
#20
1#
1%
b00000000000000000000000000101000 '
b00000000000000000000000000101101 (
b00000000000000000000000000101100 )
b00000000000000000000000000101101 *
#21
0#
#22
1#
0%
b00000000000000000000000000101101 '
b00000000000000000000000000110010 (
b00000000000000000000000000110001 )
b00000000000000000000000000110001 *
#23
0#
#24
1#
b00000000000000000000000000110001 '
b00000000000000000000000000110110 (
b00000000000000000000000000110101 )
b00000000000000000000000000110101 *
#25
0#
#26
1#
b00000000000000000000000000110101 '
b00000000000000000000000000111010 (
b00000000000000000000000000111001 )
b00000000000000000000000000111001 *
#27
0#
#28
1#
b00000000000000000000000000111001 '
b00000000000000000000000000111110 (
b00000000000000000000000000111101 )
b00000000000000000000000000111101 *
#29
0#
#30
1#
1%
b00000000000000000000000000111101 '
b00000000000000000000000001000010 (
b00000000000000000000000001000001 )
b00000000000000000000000001000010 *
#31
0#
#32
1#
0%
b00000000000000000000000001000010 '
b00000000000000000000000001000111 (
b00000000000000000000000001000110 )
b00000000000000000000000001000110 *
#33
0#
#34
1#
b00000000000000000000000001000110 '
b00000000000000000000000001001011 (
b00000000000000000000000001001010 )
b00000000000000000000000001001010 *
#35
0#
#36
1#
b00000000000000000000000001001010 '
b00000000000000000000000001001111 (
b00000000000000000000000001001110 )
b00000000000000000000000001001110 *
#37
0#
#38
1#
b00000000000000000000000001001110 '
b00000000000000000000000001010011 (
b00000000000000000000000001010010 )
b00000000000000000000000001010010 *
#39
0#
#40
1#
b00000000000000000000000001010010 '
b00000000000000000000000001010111 (
b00000000000000000000000001010110 )
b00000000000000000000000001010110 *
#41
0#
#42
1#
b00000000000000000000000001010110 '
b00000000000000000000000001011011 (
b00000000000000000000000001011010 )
b00000000000000000000000001011010 *
#43
0#
#44
1#
b00000000000000000000000001011010 '
b00000000000000000000000001011111 (
b00000000000000000000000001011110 )
b00000000000000000000000001011110 *
#45
0#
#46
1#
b00000000000000000000000001011110 '
b00000000000000000000000001100011 (
b00000000000000000000000001100010 )
b00000000000000000000000001100010 *
#47
0#
#48
1#
b00000000000000000000000001100010 '
b00000000000000000000000001100111 (
b00000000000000000000000001100110 )
b00000000000000000000000001100110 *
#49
0#
#50
1#
b00000000000000000000000001100110 '
b00000000000000000000000001101011 (
b00000000000000000000000001101010 )
b00000000000000000000000001101010 *
#51
0#
#52
1#
b00000000000000000000000001101010 '
b00000000000000000000000001101111 (
b00000000000000000000000001101110 )
b00000000000000000000000001101110 *
#53
0#
#54
1#
b00000000000000000000000001101110 '
b00000000000000000000000001110011 (
b00000000000000000000000001110010 )
b00000000000000000000000001110010 *
#55
0#
#56
1#
b00000000000000000000000001110010 '
b00000000000000000000000001110111 (
b00000000000000000000000001110110 )
b00000000000000000000000001110110 *
#57
0#
#58
1#
b00000000000000000000000001110110 '
b00000000000000000000000001111011 (
b00000000000000000000000001111010 )
b00000000000000000000000001111010 *
#59
0#
#60
1#
1$
b00000000000000000000000000000000 '
b00000000000000000000000000000101 (
b00000000000000000000000000000100 )
b00000000000000000000000000000100 *
#61
0#
#62
1#
0$
b00000000000000000000000000000100 '
b00000000000000000000000000001001 (
b00000000000000000000000000001000 )
b00000000000000000000000000001000 *
#63
0#
#64
1#
b00000000000000000000000000001000 '
b00000000000000000000000000001101 (
b00000000000000000000000000001100 )
b00000000000000000000000000001100 *
#65
0#
#66
1#
b00000000000000000000000000001100 '
b00000000000000000000000000010001 (
b00000000000000000000000000010000 )
b00000000000000000000000000010000 *
#67
0#
#68
1#
b00000000000000000000000000010000 '
b00000000000000000000000000010101 (
b00000000000000000000000000010100 )
b00000000000000000000000000010100 *
#69
0#
#70
1#
b00000000000000000000000000010100 '
b00000000000000000000000000011001 (
b00000000000000000000000000011000 )
b00000000000000000000000000011000 *
#71
0#
#72
1#
b00000000000000000000000000011000 '
b00000000000000000000000000011101 (
b00000000000000000000000000011100 )
b00000000000000000000000000011100 *
#73
0#
#74
1#
b00000000000000000000000000011100 '
b00000000000000000000000000100001 (
b00000000000000000000000000100000 )
b00000000000000000000000000100000 *
#75
0#
#76
1#
b00000000000000000000000000100000 '
b00000000000000000000000000100101 (
b00000000000000000000000000100100 )
b00000000000000000000000000100100 *
#77
0#
#78
1#
b00000000000000000000000000100100 '
b00000000000000000000000000101001 (
b00000000000000000000000000101000 )
b00000000000000000000000000101000 *
#79
0#
#80
1#
b00000000000000000000000000101000 '
b00000000000000000000000000101101 (
b00000000000000000000000000101100 )
b00000000000000000000000000101100 *
#81
0#
#82
1#
b00000000000000000000000000101100 '
b00000000000000000000000000110001 (
b00000000000000000000000000110000 )
b00000000000000000000000000110000 *
#83
0#
#84
1#
b00000000000000000000000000110000 '
b00000000000000000000000000110101 (
b00000000000000000000000000110100 )
b00000000000000000000000000110100 *
#85
0#
#86
1#
b00000000000000000000000000110100 '
b00000000000000000000000000111001 (
b00000000000000000000000000111000 )
b00000000000000000000000000111000 *
#87
0#
#88
1#
b00000000000000000000000000111000 '
b00000000000000000000000000111101 (
b00000000000000000000000000111100 )
b00000000000000000000000000111100 *
#89
0#
#90
1#
b00000000000000000000000000111100 '
b00000000000000000000000001000001 (
b00000000000000000000000001000000 )
b00000000000000000000000001000000 *
#91
0#
#92
1#
b00000000000000000000000001000000 '
b00000000000000000000000001000101 (
b00000000000000000000000001000100 )
b00000000000000000000000001000100 *
#93
0#
#94
1#
b00000000000000000000000001000100 '
b00000000000000000000000001001001 (
b00000000000000000000000001001000 )
b00000000000000000000000001001000 *
#95
0#
#96
1#
b00000000000000000000000001001000 '
b00000000000000000000000001001101 (
b00000000000000000000000001001100 )
b00000000000000000000000001001100 *
#97
0#
#98
1#
b00000000000000000000000001001100 '
b00000000000000000000000001010001 (
b00000000000000000000000001010000 )
b00000000000000000000000001010000 *
#99
0#
#100
1#
b00000000000000000000000001010000 '
b00000000000000000000000001010101 (
b00000000000000000000000001010100 )
b00000000000000000000000001010100 *
#101
0#
#102
1#
b00000000000000000000000001010100 '
b00000000000000000000000001011001 (
b00000000000000000000000001011000 )
b00000000000000000000000001011000 *
#103
0#
#104
1#
b00000000000000000000000001011000 '
b00000000000000000000000001011101 (
b00000000000000000000000001011100 )
b00000000000000000000000001011100 *
#105
0#
#106
1#
b00000000000000000000000001011100 '
b00000000000000000000000001100001 (
b00000000000000000000000001100000 )
b00000000000000000000000001100000 *
#107
0#
#108
1#
b00000000000000000000000001100000 '
b00000000000000000000000001100101 (
b00000000000000000000000001100100 )
b00000000000000000000000001100100 *
#109
0#
#110
1#
b00000000000000000000000001100100 '
b00000000000000000000000001101001 (
b00000000000000000000000001101000 )
b00000000000000000000000001101000 *
#111
0#
#112
1#
b00000000000000000000000001101000 '
b00000000000000000000000001101101 (
b00000000000000000000000001101100 )
b00000000000000000000000001101100 *
#113
0#
#114
1#
b00000000000000000000000001101100 '
b00000000000000000000000001110001 (
b00000000000000000000000001110000 )
b00000000000000000000000001110000 *
#115
0#
#116
1#
b00000000000000000000000001110000 '
b00000000000000000000000001110101 (
b00000000000000000000000001110100 )
b00000000000000000000000001110100 *
#117
0#
#118
1#
b00000000000000000000000001110100 '
b00000000000000000000000001111001 (
b00000000000000000000000001111000 )
b00000000000000000000000001111000 *
#119
0#
#120
1#
b00000000000000000000000001111000 '
b00000000000000000000000001111101 (
b00000000000000000000000001111100 )
b00000000000000000000000001111100 *
#121
0#
#122
1#
b00000000000000000000000001111100 '
b00000000000000000000000010000001 (
b00000000000000000000000010000000 )
b00000000000000000000000010000000 *
#123
0#
#124
1#
b00000000000000000000000010000000 '
b00000000000000000000000010000101 (
b00000000000000000000000010000100 )
b00000000000000000000000010000100 *
#125
0#
#126
1#
b00000000000000000000000010000100 '
b00000000000000000000000010001001 (
b00000000000000000000000010001000 )
b00000000000000000000000010001000 *
#127
0#
#128
1#
b00000000000000000000000010001000 '
b00000000000000000000000010001101 (
b00000000000000000000000010001100 )
b00000000000000000000000010001100 *
#129
0#
#130
1#
b00000000000000000000000010001100 '
b00000000000000000000000010010001 (
b00000000000000000000000010010000 )
b00000000000000000000000010010000 *
#131
0#
#132
1#
b00000000000000000000000010010000 '
b00000000000000000000000010010101 (
b00000000000000000000000010010100 )
b00000000000000000000000010010100 *
#133
0#
#134
1#
b00000000000000000000000010010100 '
b00000000000000000000000010011001 (
b00000000000000000000000010011000 )
b00000000000000000000000010011000 *
#135
0#
#136
1#
b00000000000000000000000010011000 '
b00000000000000000000000010011101 (
b00000000000000000000000010011100 )
b00000000000000000000000010011100 *
#137
0#
#138
1#
b00000000000000000000000010011100 '
b00000000000000000000000010100001 (
b00000000000000000000000010100000 )
b00000000000000000000000010100000 *
#139
0#
#140
1#
b00000000000000000000000010100000 '
b00000000000000000000000010100101 (
b00000000000000000000000010100100 )
b00000000000000000000000010100100 *
#141
0#
#142
1#
b00000000000000000000000010100100 '
b00000000000000000000000010101001 (
b00000000000000000000000010101000 )
b00000000000000000000000010101000 *
#143
0#
#144
1#
b00000000000000000000000010101000 '
b00000000000000000000000010101101 (
b00000000000000000000000010101100 )
b00000000000000000000000010101100 *
#145
0#
#146
1#
b00000000000000000000000010101100 '
b00000000000000000000000010110001 (
b00000000000000000000000010110000 )
b00000000000000000000000010110000 *
#147
0#
#148
1#
b00000000000000000000000010110000 '
b00000000000000000000000010110101 (
b00000000000000000000000010110100 )
b00000000000000000000000010110100 *
#149
0#
#150
1#
b00000000000000000000000010110100 '
b00000000000000000000000010111001 (
b00000000000000000000000010111000 )
b00000000000000000000000010111000 *
#151
0#
#152
1#
b00000000000000000000000010111000 '
b00000000000000000000000010111101 (
b00000000000000000000000010111100 )
b00000000000000000000000010111100 *
#153
0#
#154
1#
b00000000000000000000000010111100 '
b00000000000000000000000011000001 (
b00000000000000000000000011000000 )
b00000000000000000000000011000000 *
#155
0#
#156
1#
b00000000000000000000000011000000 '
b00000000000000000000000011000101 (
b00000000000000000000000011000100 )
b00000000000000000000000011000100 *
#157
0#
#158
1#
b00000000000000000000000011000100 '
b00000000000000000000000011001001 (
b00000000000000000000000011001000 )
b00000000000000000000000011001000 *
#159
0#
#160
1#
b00000000000000000000000011001000 '
b00000000000000000000000011001101 (
b00000000000000000000000011001100 )
b00000000000000000000000011001100 *
#161
0#
#162
1#
b00000000000000000000000011001100 '
b00000000000000000000000011010001 (
b00000000000000000000000011010000 )
b00000000000000000000000011010000 *
#163
0#
#164
1#
b00000000000000000000000011010000 '
b00000000000000000000000011010101 (
b00000000000000000000000011010100 )
b00000000000000000000000011010100 *
#165
0#
#166
1#
b00000000000000000000000011010100 '
b00000000000000000000000011011001 (
b00000000000000000000000011011000 )
b00000000000000000000000011011000 *
#167
0#
#168
1#
b00000000000000000000000011011000 '
b00000000000000000000000011011101 (
b00000000000000000000000011011100 )
b00000000000000000000000011011100 *
#169
0#
#170
1#
b00000000000000000000000011011100 '
b00000000000000000000000011100001 (
b00000000000000000000000011100000 )
b00000000000000000000000011100000 *
#171
0#
#172
1#
b00000000000000000000000011100000 '
b00000000000000000000000011100101 (
b00000000000000000000000011100100 )
b00000000000000000000000011100100 *
#173
0#
#174
1#
b00000000000000000000000011100100 '
b00000000000000000000000011101001 (
b00000000000000000000000011101000 )
b00000000000000000000000011101000 *
#175
0#
#176
1#
b00000000000000000000000011101000 '
b00000000000000000000000011101101 (
b00000000000000000000000011101100 )
b00000000000000000000000011101100 *
#177
0#
#178
1#
b00000000000000000000000011101100 '
b00000000000000000000000011110001 (
b00000000000000000000000011110000 )
b00000000000000000000000011110000 *
#179
0#
#180
1#
b00000000000000000000000011110000 '
b00000000000000000000000011110101 (
b00000000000000000000000011110100 )
b00000000000000000000000011110100 *
#181
0#
#182
1#
b00000000000000000000000011110100 '
b00000000000000000000000011111001 (
b00000000000000000000000011111000 )
b00000000000000000000000011111000 *
#183
0#
#184
1#
b00000000000000000000000011111000 '
b00000000000000000000000011111101 (
b00000000000000000000000011111100 )
b00000000000000000000000011111100 *
#185
0#
#186
1#
b00000000000000000000000011111100 '
b00000000000000000000000100000001 (
b00000000000000000000000100000000 )
b00000000000000000000000100000000 *
#187
0#
#188
1#
b00000000000000000000000100000000 '
b00000000000000000000000100000101 (
b00000000000000000000000100000100 )
b00000000000000000000000100000100 *
#189
0#
#190
1#
b00000000000000000000000100000100 '
b00000000000000000000000100001001 (
b00000000000000000000000100001000 )
b00000000000000000000000100001000 *
#191
0#
#192
1#
b00000000000000000000000100001000 '
b00000000000000000000000100001101 (
b00000000000000000000000100001100 )
b00000000000000000000000100001100 *
#193
0#
#194
1#
b00000000000000000000000100001100 '
b00000000000000000000000100010001 (
b00000000000000000000000100010000 )
b00000000000000000000000100010000 *
#195
0#
#196
1#
b00000000000000000000000100010000 '
b00000000000000000000000100010101 (
b00000000000000000000000100010100 )
b00000000000000000000000100010100 *
#197
0#
#198
1#
b00000000000000000000000100010100 '
b00000000000000000000000100011001 (
b00000000000000000000000100011000 )
b00000000000000000000000100011000 *
