Debugged_cpu/rf.sv
module rf #(
    parameter  A_WIDTH = 5,
                D_WIDTH = 32
) (
    input logic clk,
    input logic we3,
    input logic [A_WIDTH-1:0] ad1,
    input logic [A_WIDTH-1:0] ad2,
    input logic [A_WIDTH-1:0] ad3,
    input logic [D_WIDTH-1:0] wd3,
    output logic [D_WIDTH-1:0] a0,
    output logic [D_WIDTH-1:0] rd1,
    output logic [D_WIDTH-1:0] rd2
);

    logic [D_WIDTH-1:0] rf_array [2**A_WIDTH-1:0];

    always_comb begin
        rd1 = rf_array[ad1];
        rd2 = rf_array[ad2];
    end

    initial begin
        for (int i = 0; i < $size(rf_array); i++) begin
            rf_array[i] = 32'b0;
        end
    end

    always_ff @(posedge clk) begin
        if(we3) rf_array[ad3] <= wd3; 
    end
    
    assign a0 = rf_array[10];
endmodule

Debugged_cpu/alu.sv
module alu #(
    parameter D_WIDTH = 32
)(
    input logic alusrc,
    input logic [2:0] aluctrl,
    input logic [D_WIDTH-1:0] aluop1,
    input logic [D_WIDTH-1:0] immop,
    input logic [D_WIDTH-1:0] regop2,
    output logic [D_WIDTH-1:0] aluout,
    output logic eq
);
    
    logic [D_WIDTH-1:0] aluop2;
    assign aluop2 = alusrc ? immop : regop2;
    always_comb begin
        
        case (aluctrl)
            3'b000: aluout = aluop1 + aluop2;
            3'b001: aluout = 32'b0;
            3'b010: aluout = 32'b0;
            3'b011: aluout = 32'b0;
            3'b100: aluout = 32'b0;
            3'b101: aluout = 32'b0;
            3'b110: aluout = 32'b0;
            default: aluout = 0;
        endcase
    end


    assign eq = (aluop1 == aluop2);

    
endmodule

omar/RISC-V-1/temp completed/signextender.sv
module signextender(
    input logic [31:0] instruction,
    input logic [2:0] immsrc,
    output logic [31:0] immop
);
    logic [11:0] uimm;
    
    always_comb begin
        case (immsrc)    
            3'b000: uimm = instruction[31:20]; // immediate
            // 3'b001: uimm = instruction[31:12]; // upper immediate
            // 3'b010: uimm = {instruction[31:25], instruction[11:7]}; // store
            3'b011: uimm = {instruction[31], instruction[7], instruction[30:25], instruction[11:8]}; // branch
            // 3'b100: uimm = {instruction[31], instruction[19:12], instruction[20], instruction[30:21]}; // jump
            default: uimm = 12'b0;
        endcase
    end

    // for now this will work, however for upper immediate and jump a case will be required
    assign immop = {{5'd20{uimm[11]}}, uimm[11:0]};
    
endmodule

Debugged_cpu/instrmem.sv
module instrmem #(
    parameter   A_WIDTH = 32,
                D_WIDTH = 8        
) (
    input [A_WIDTH-1:0] address,
    output [31:0] dout
);
    logic [D_WIDTH-1:0] rom_array [2000:0];
    
    initial begin 
        $display("Loading rom.");
        $readmemh("program.hex", rom_array);
        $display("Program written to ROM successfully");
    end;

    assign dout = {{rom_array[address]}, {rom_array[address+1]}, {rom_array[address+2]}, {rom_array[address+3]}}; 

endmodule

omar/RISC-V-1/temp completed/pcountunit.sv

module pcountunit #(
    parameter WIDTH = 32
) (
    input logic pcsrc,
    input logic clk,
    input logic rst,
    input logic [WIDTH-1:0] immop,
    output logic [WIDTH-1:0] pc
);

    logic [WIDTH-1:0] next_pc;
    logic [WIDTH-1:0] branch_pc;
    
    always_comb begin
        branch_pc = pc + immop;
        next_pc = pcsrc ? branch_pc : pc + 4;    
    end

    always_ff @(posedge clk) begin
        if(rst) pc <= 32'b0;
        else pc <= next_pc;
    end



endmodule

Debugged_cpu/controlunit.sv
module controlunit(
    input logic [31:0] instruction,
    input logic eq,
    output logic regwrite,
    output logic [2:0] aluctrl,
    output logic alusrc,
    output logic pcsrc,
    output logic [2:0] immsrc
);
    logic [6:0] opcode;
    assign opcode = instruction[6:0];

    always_comb begin
        case (opcode)
            7'd19: begin
                aluctrl = instruction[14:12];
                alusrc = 1'b1;
                regwrite = 1'b1;
                immsrc = 3'b000;
                pcsrc = 1'b0;
            end
            7'd99:begin
                aluctrl = 3'b111;
                alusrc = 1'b0;
                regwrite = 1'b0;
                immsrc = 3'b011;
                pcsrc = !eq;
            end
            default: begin
                aluctrl = 3'b0;
                alusrc = 1'b0;
                regwrite = 1'b0;
                immsrc = 3'b0;
                pcsrc = 1'b1;
            end
        endcase
    end
    
    
endmodule

Debugged_cpu/cpu.sv
module cpu #(
    parameter WIDTH = 32
) (
    input logic clk, 
    input logic rst,
    output logic [WIDTH-1:0] a0_output,
    output logic [WIDTH-1:0] rf_dout1,
    output logic [WIDTH-1:0] rf_dout2,
    output logic [WIDTH-1:0] interm_immop,
    output logic [4:0] rd_add,
    output logic [WIDTH-1:0] prog_addr,
    logic [WIDTH-1:0] interm_ins
    
);

logic [WIDTH-1:0] rf_din;
logic [2:0] interm_aluctrl;
logic [2:0] interm_immsrc;
logic interm_alusrc;
logic interm_eq;
logic interm_pcsrc;
logic write_en;

assign rd_add = interm_ins[19:15];

controlunit ctrlunit(
    .instruction(interm_ins), //in
    .eq(interm_eq), //in
    .regwrite(write_en), //out
    .aluctrl(interm_aluctrl), //out
    .alusrc(interm_alusrc), //out
    .pcsrc(interm_pcsrc), //out
    .immsrc(interm_immsrc) //out
);

pcountunit programcounter(
    .clk(clk), //in
    .rst(rst), //in
    .pcsrc(interm_pcsrc), //in
    .immop(interm_immop), //in
    .pc(prog_addr) //out
);

instrmem programmem(
    .address(prog_addr),
    .dout(interm_ins)
);

signextender sgnextend(
    .instruction(interm_ins),
    .immsrc(interm_immsrc),
    .immop(interm_immop)
);


alu alu(
    .alusrc(interm_alusrc),
    .aluctrl(interm_aluctrl),
    .aluop1(rf_dout1),
    .immop(interm_immop),
    .regop2(rf_dout2),
    .aluout(rf_din),
    .eq(interm_eq)
);

rf registerfile(
    .clk(clk), //in
    .we3(write_en), //in
    .ad1(interm_ins[19:15]), //in
    .ad2(interm_ins[24:20]), //in
    .ad3(interm_ins[11:7]), //in
    .wd3(rf_din), //in
    .a0(a0_output), //out
    .rd1(rf_dout1), //out
    .rd2(rf_dout2) //out
);



endmodule

Debugged_cpu/cpu.vcd
$version Generated by VerilatedVcd $end
$date Fri Nov 25 11:48:55 2022 $end
$timescale 1ps $end

 $scope module TOP $end
  $var wire 32 L a0_output [31:0] $end
  $var wire  1 J clk $end
  $var wire 32 O interm_immop [31:0] $end
  $var wire 32 R interm_ins [31:0] $end
  $var wire 32 Q prog_addr [31:0] $end
  $var wire  5 P rd_add [4:0] $end
  $var wire 32 M rf_dout1 [31:0] $end
  $var wire 32 N rf_dout2 [31:0] $end
  $var wire  1 K rst $end
  $scope module cpu $end
   $var wire 32 [ WIDTH [31:0] $end
   $var wire 32 L a0_output [31:0] $end
   $var wire  1 J clk $end
   $var wire  3 $ interm_aluctrl [2:0] $end
   $var wire  1 T interm_alusrc $end
   $var wire  1 U interm_eq $end
   $var wire 32 O interm_immop [31:0] $end
   $var wire  3 % interm_immsrc [2:0] $end
   $var wire 32 R interm_ins [31:0] $end
   $var wire  1 V interm_pcsrc $end
   $var wire 32 Q prog_addr [31:0] $end
   $var wire  5 P rd_add [4:0] $end
   $var wire 32 S rf_din [31:0] $end
   $var wire 32 M rf_dout1 [31:0] $end
   $var wire 32 N rf_dout2 [31:0] $end
   $var wire  1 K rst $end
   $var wire  1 T write_en $end
   $scope module alu $end
    $var wire 32 [ D_WIDTH [31:0] $end
    $var wire  3 $ aluctrl [2:0] $end
    $var wire 32 M aluop1 [31:0] $end
    $var wire 32 & aluop2 [31:0] $end
    $var wire 32 S aluout [31:0] $end
    $var wire  1 T alusrc $end
    $var wire  1 U eq $end
    $var wire 32 O immop [31:0] $end
    $var wire 32 N regop2 [31:0] $end
   $upscope $end
   $scope module ctrlunit $end
    $var wire  3 $ aluctrl [2:0] $end
    $var wire  1 T alusrc $end
    $var wire  1 U eq $end
    $var wire  3 % immsrc [2:0] $end
    $var wire 32 R instruction [31:0] $end
    $var wire  7 W opcode [6:0] $end
    $var wire  1 V pcsrc $end
    $var wire  1 T regwrite $end
   $upscope $end
   $scope module programcounter $end
    $var wire 32 [ WIDTH [31:0] $end
    $var wire 32 ( branch_pc [31:0] $end
    $var wire  1 J clk $end
    $var wire 32 O immop [31:0] $end
    $var wire 32 ' next_pc [31:0] $end
    $var wire 32 Q pc [31:0] $end
    $var wire  1 V pcsrc $end
    $var wire  1 K rst $end
   $upscope $end
   $scope module programmem $end
    $var wire 32 [ A_WIDTH [31:0] $end
    $var wire 32 \ D_WIDTH [31:0] $end
    $var wire 32 Q address [31:0] $end
    $var wire 32 R dout [31:0] $end
   $upscope $end
   $scope module registerfile $end
    $var wire 32 ] A_WIDTH [31:0] $end
    $var wire 32 [ D_WIDTH [31:0] $end
    $var wire 32 L a0 [31:0] $end
    $var wire  5 X ad1 [4:0] $end
    $var wire  5 Y ad2 [4:0] $end
    $var wire  5 Z ad3 [4:0] $end
    $var wire  1 J clk $end
    $var wire 32 M rd1 [31:0] $end
    $var wire 32 N rd2 [31:0] $end
    $var wire 32 ) rf_array[0] [31:0] $end
    $var wire 32 3 rf_array[10] [31:0] $end
    $var wire 32 4 rf_array[11] [31:0] $end
    $var wire 32 5 rf_array[12] [31:0] $end
    $var wire 32 6 rf_array[13] [31:0] $end
    $var wire 32 7 rf_array[14] [31:0] $end
    $var wire 32 8 rf_array[15] [31:0] $end
    $var wire 32 9 rf_array[16] [31:0] $end
    $var wire 32 : rf_array[17] [31:0] $end
    $var wire 32 ; rf_array[18] [31:0] $end
    $var wire 32 < rf_array[19] [31:0] $end
    $var wire 32 * rf_array[1] [31:0] $end
    $var wire 32 = rf_array[20] [31:0] $end
    $var wire 32 > rf_array[21] [31:0] $end
    $var wire 32 ? rf_array[22] [31:0] $end
    $var wire 32 @ rf_array[23] [31:0] $end
    $var wire 32 A rf_array[24] [31:0] $end
    $var wire 32 B rf_array[25] [31:0] $end
    $var wire 32 C rf_array[26] [31:0] $end
    $var wire 32 D rf_array[27] [31:0] $end
    $var wire 32 E rf_array[28] [31:0] $end
    $var wire 32 F rf_array[29] [31:0] $end
    $var wire 32 + rf_array[2] [31:0] $end
    $var wire 32 G rf_array[30] [31:0] $end
    $var wire 32 H rf_array[31] [31:0] $end
    $var wire 32 , rf_array[3] [31:0] $end
    $var wire 32 - rf_array[4] [31:0] $end
    $var wire 32 . rf_array[5] [31:0] $end
    $var wire 32 / rf_array[6] [31:0] $end
    $var wire 32 0 rf_array[7] [31:0] $end
    $var wire 32 1 rf_array[8] [31:0] $end
    $var wire 32 2 rf_array[9] [31:0] $end
    $var wire 32 S wd3 [31:0] $end
    $var wire  1 T we3 $end
    $scope module unnamedblk1 $end
     $var wire 32 # i [31:0] $end
    $upscope $end
   $upscope $end
   $scope module sgnextend $end
    $var wire 32 O immop [31:0] $end
    $var wire  3 % immsrc [2:0] $end
    $var wire 32 R instruction [31:0] $end
    $var wire 12 I uimm [11:0] $end
   $upscope $end
  $upscope $end
 $upscope $end
$enddefinitions $end


#0
b00000000000000000000000000000000 #
b000 $
b000 %
b00000000000000000000000000000000 &
b00000000000000000000000000000000 '
b00000000000000000000000000000000 (
b00000000000000000000000000000000 )
b00000000000000000000000000000000 *
b00000000000000000000000000000000 +
b00000000000000000000000000000000 ,
b00000000000000000000000000000000 -
b00000000000000000000000000000000 .
b00000000000000000000000000000000 /
b00000000000000000000000000000000 0
b00000000000000000000000000000000 1
b00000000000000000000000000000000 2
b00000000000000000000000000000000 3
b00000000000000000000000000000000 4
b00000000000000000000000000000000 5
b00000000000000000000000000000000 6
b00000000000000000000000000000000 7
b00000000000000000000000000000000 8
b00000000000000000000000000000000 9
b00000000000000000000000000000000 :
b00000000000000000000000000000000 ;
b00000000000000000000000000000000 <
b00000000000000000000000000000000 =
b00000000000000000000000000000000 >
b00000000000000000000000000000000 ?
b00000000000000000000000000000000 @
b00000000000000000000000000000000 A
b00000000000000000000000000000000 B
b00000000000000000000000000000000 C
b00000000000000000000000000000000 D
b00000000000000000000000000000000 E
b00000000000000000000000000000000 F
b00000000000000000000000000000000 G
b00000000000000000000000000000000 H
b000000000000 I
0J
0K
b00000000000000000000000000000000 L
b00000000000000000000000000000000 M
b00000000000000000000000000000000 N
b00000000000000000000000000000000 O
b00000 P
b00000000000000000000000000000000 Q
b00000000000000000000000000000000 R
b00000000000000000000000000000000 S
0T
1U
1V
b0000000 W
b00000 X
b00000 Y
b00000 Z
b00000000000000000000000000100000 [
b00000000000000000000000000001000 \
b00000000000000000000000000000101 ]
#1
b00000000000000000000000000100000 #
b00000000000000000000000011111111 &
b00000000000000000000000000000100 '
b00000000000000000000000011111111 (
b000011111111 I
1J
b00000000000000000000000011111111 O
b00001111111100000000001100010011 R
b00000000000000000000000011111111 S
1T
0U
0V
b0010011 W
b11111 Y
b00110 Z
#2
0J
#3
b00000000000000000000000000000000 &
b00000000000000000000000000001000 '
b00000000000000000000000000000100 (
b00000000000000000000000011111111 /
b000000000000 I
1J
b00000000000000000000000000000000 O
b00000000000000000000000000000100 Q
b00000000000000000000010100010011 R
b00000000000000000000000000000000 S
1U
b00000 Y
b01010 Z
#4
0J
#5
b00000000000000000000000011110000 &
b00000000000000000000000000001100 '
b00000000000000000000000011111000 (
b000011110000 I
1J
b00000000000000000000000011110000 O
b00000000000000000000000000001000 Q
b00001111000000000000010110010011 R
b00000000000000000000000011110000 S
0U
b10000 Y
b01011 Z
#6
0J
#7
b00000000000000000000000000000000 &
b00000000000000000000000000010000 '
b00000000000000000000000000001100 (
b00000000000000000000000011110000 4
b000000000000 I
1J
b00000000000000000000000011110000 M
b00000000000000000000000000000000 O
b01011 P
b00000000000000000000000000001100 Q
b00000000000001011000010100010011 R
b01011 X
b00000 Y
b01010 Z
#8
0J
#9
b00000000000000000000000000000001 &
b00000000000000000000000000010100 '
b00000000000000000000000000010001 (
b00000000000000000000000011110000 3
b000000000001 I
1J
b00000000000000000000000011110000 L
b00000000000000000000000000000001 O
b00000000000000000000000000010000 Q
b00000000000101011000010110010011 R
b00000000000000000000000011110001 S
b00001 Y
b01011 Z
#10
0J
#11
b111 $
b011 %
b00000000000000000000000011111111 &
b00000000000000000000000000001100 '
b00000000000000000000000000001100 (
b00000000000000000000000011110001 4
b111111111000 I
1J
b00000000000000000000000011110001 M
b00000000000000000000000011111111 N
b11111111111111111111111111111000 O
b00000000000000000000000000010100 Q
b11111110011001011001100011100011 R
b00000000000000000000000000000000 S
0T
1V
b1100011 W
b00110 Y
b10001 Z
#12
0J
#13
b000 $
b000 %
b00000000000000000000000000000000 &
b00000000000000000000000000010000 '
b000000000000 I
1J
b00000000000000000000000000000000 N
b00000000000000000000000000000000 O
b00000000000000000000000000001100 Q
b00000000000001011000010100010011 R
b00000000000000000000000011110001 S
1T
0V
b0010011 W
b00000 Y
b01010 Z
#14
0J
#15
b00000000000000000000000000000001 &
b00000000000000000000000000010100 '
b00000000000000000000000000010001 (
b00000000000000000000000011110001 3
b000000000001 I
1J
b00000000000000000000000011110001 L
b00000000000000000000000000000001 O
b00000000000000000000000000010000 Q
b00000000000101011000010110010011 R
b00000000000000000000000011110010 S
b00001 Y
b01011 Z
#16
0J
#17
b111 $
b011 %
b00000000000000000000000011111111 &
b00000000000000000000000000001100 '
b00000000000000000000000000001100 (
b00000000000000000000000011110010 4
b111111111000 I
1J
b00000000000000000000000011110010 M
b00000000000000000000000011111111 N
b11111111111111111111111111111000 O
b00000000000000000000000000010100 Q
b11111110011001011001100011100011 R
b00000000000000000000000000000000 S
0T
1V
b1100011 W
b00110 Y
b10001 Z
#18
0J
#19
b000 $
b000 %
b00000000000000000000000000000000 &
b00000000000000000000000000010000 '
b000000000000 I
1J
b00000000000000000000000000000000 N
b00000000000000000000000000000000 O
b00000000000000000000000000001100 Q
b00000000000001011000010100010011 R
b00000000000000000000000011110010 S
1T
0V
b0010011 W
b00000 Y
b01010 Z
#20
0J
#21
b00000000000000000000000000000001 &
b00000000000000000000000000010100 '
b00000000000000000000000000010001 (
b00000000000000000000000011110010 3
b000000000001 I
1J
b00000000000000000000000011110010 L
b00000000000000000000000000000001 O
b00000000000000000000000000010000 Q
b00000000000101011000010110010011 R
b00000000000000000000000011110011 S
b00001 Y
b01011 Z
#22
0J
#23
b111 $
b011 %
b00000000000000000000000011111111 &
b00000000000000000000000000001100 '
b00000000000000000000000000001100 (
b00000000000000000000000011110011 4
b111111111000 I
1J
b00000000000000000000000011110011 M
b00000000000000000000000011111111 N
b11111111111111111111111111111000 O
b00000000000000000000000000010100 Q
b11111110011001011001100011100011 R
b00000000000000000000000000000000 S
0T
1V
b1100011 W
b00110 Y
b10001 Z
#24
0J
#25
b000 $
b000 %
b00000000000000000000000000000000 &
b00000000000000000000000000010000 '
b000000000000 I
1J
b00000000000000000000000000000000 N
b00000000000000000000000000000000 O
b00000000000000000000000000001100 Q
b00000000000001011000010100010011 R
b00000000000000000000000011110011 S
1T
0V
b0010011 W
b00000 Y
b01010 Z
#26
0J
#27
b00000000000000000000000000000001 &
b00000000000000000000000000010100 '
b00000000000000000000000000010001 (
b00000000000000000000000011110011 3
b000000000001 I
1J
b00000000000000000000000011110011 L
b00000000000000000000000000000001 O
b00000000000000000000000000010000 Q
b00000000000101011000010110010011 R
b00000000000000000000000011110100 S
b00001 Y
b01011 Z
#28
0J
#29
b111 $
b011 %
b00000000000000000000000011111111 &
b00000000000000000000000000001100 '
b00000000000000000000000000001100 (
b00000000000000000000000011110100 4
b111111111000 I
1J
b00000000000000000000000011110100 M
b00000000000000000000000011111111 N
b11111111111111111111111111111000 O
b00000000000000000000000000010100 Q
b11111110011001011001100011100011 R
b00000000000000000000000000000000 S
0T
1V
b1100011 W
b00110 Y
b10001 Z
#30
0J
#31
b000 $
b000 %
b00000000000000000000000000000000 &
b00000000000000000000000000010000 '
b000000000000 I
1J
b00000000000000000000000000000000 N
b00000000000000000000000000000000 O
b00000000000000000000000000001100 Q
b00000000000001011000010100010011 R
b00000000000000000000000011110100 S
1T
0V
b0010011 W
b00000 Y
b01010 Z
#32
0J
#33
b00000000000000000000000000000001 &
b00000000000000000000000000010100 '
b00000000000000000000000000010001 (
b00000000000000000000000011110100 3
b000000000001 I
1J
b00000000000000000000000011110100 L
b00000000000000000000000000000001 O
b00000000000000000000000000010000 Q
b00000000000101011000010110010011 R
b00000000000000000000000011110101 S
b00001 Y
b01011 Z
#34
0J
#35
b111 $
b011 %
b00000000000000000000000011111111 &
b00000000000000000000000000001100 '
b00000000000000000000000000001100 (
b00000000000000000000000011110101 4
b111111111000 I
1J
b00000000000000000000000011110101 M
b00000000000000000000000011111111 N
b11111111111111111111111111111000 O
b00000000000000000000000000010100 Q
b11111110011001011001100011100011 R
b00000000000000000000000000000000 S
0T
1V
b1100011 W
b00110 Y
b10001 Z
#36
0J
#37
b000 $
b000 %
b00000000000000000000000000000000 &
b00000000000000000000000000010000 '
b000000000000 I
1J
b00000000000000000000000000000000 N
b00000000000000000000000000000000 O
b00000000000000000000000000001100 Q
b00000000000001011000010100010011 R
b00000000000000000000000011110101 S
1T
0V
b0010011 W
b00000 Y
b01010 Z
#38
0J
#39
b00000000000000000000000000000001 &
b00000000000000000000000000010100 '
b00000000000000000000000000010001 (
b00000000000000000000000011110101 3
b000000000001 I
1J
b00000000000000000000000011110101 L
b00000000000000000000000000000001 O
b00000000000000000000000000010000 Q
b00000000000101011000010110010011 R
b00000000000000000000000011110110 S
b00001 Y
b01011 Z
#40
0J
#41
b111 $
b011 %
b00000000000000000000000011111111 &
b00000000000000000000000000001100 '
b00000000000000000000000000001100 (
b00000000000000000000000011110110 4
b111111111000 I
1J
b00000000000000000000000011110110 M
b00000000000000000000000011111111 N
b11111111111111111111111111111000 O
b00000000000000000000000000010100 Q
b11111110011001011001100011100011 R
b00000000000000000000000000000000 S
0T
1V
b1100011 W
b00110 Y
b10001 Z
#42
0J
#43
b000 $
b000 %
b00000000000000000000000000000000 &
b00000000000000000000000000010000 '
b000000000000 I
1J
b00000000000000000000000000000000 N
b00000000000000000000000000000000 O
b00000000000000000000000000001100 Q
b00000000000001011000010100010011 R
b00000000000000000000000011110110 S
1T
0V
b0010011 W
b00000 Y
b01010 Z
#44
0J
#45
b00000000000000000000000000000001 &
b00000000000000000000000000010100 '
b00000000000000000000000000010001 (
b00000000000000000000000011110110 3
b000000000001 I
1J
b00000000000000000000000011110110 L
b00000000000000000000000000000001 O
b00000000000000000000000000010000 Q
b00000000000101011000010110010011 R
b00000000000000000000000011110111 S
b00001 Y
b01011 Z
#46
0J
#47
b111 $
b011 %
b00000000000000000000000011111111 &
b00000000000000000000000000001100 '
b00000000000000000000000000001100 (
b00000000000000000000000011110111 4
b111111111000 I
1J
b00000000000000000000000011110111 M
b00000000000000000000000011111111 N
b11111111111111111111111111111000 O
b00000000000000000000000000010100 Q
b11111110011001011001100011100011 R
b00000000000000000000000000000000 S
0T
1V
b1100011 W
b00110 Y
b10001 Z
#48
0J
#49
b000 $
b000 %
b00000000000000000000000000000000 &
b00000000000000000000000000010000 '
b000000000000 I
1J
b00000000000000000000000000000000 N
b00000000000000000000000000000000 O
b00000000000000000000000000001100 Q
b00000000000001011000010100010011 R
b00000000000000000000000011110111 S
1T
0V
b0010011 W
b00000 Y
b01010 Z
#50
0J
#51
b00000000000000000000000000000001 &
b00000000000000000000000000010100 '
b00000000000000000000000000010001 (
b00000000000000000000000011110111 3
b000000000001 I
1J
b00000000000000000000000011110111 L
b00000000000000000000000000000001 O
b00000000000000000000000000010000 Q
b00000000000101011000010110010011 R
b00000000000000000000000011111000 S
b00001 Y
b01011 Z
#52
0J
#53
b111 $
b011 %
b00000000000000000000000011111111 &
b00000000000000000000000000001100 '
b00000000000000000000000000001100 (
b00000000000000000000000011111000 4
b111111111000 I
1J
b00000000000000000000000011111000 M
b00000000000000000000000011111111 N
b11111111111111111111111111111000 O
b00000000000000000000000000010100 Q
b11111110011001011001100011100011 R
b00000000000000000000000000000000 S
0T
1V
b1100011 W
b00110 Y
b10001 Z
#54
0J
#55
b000 $
b000 %
b00000000000000000000000000000000 &
b00000000000000000000000000010000 '
b000000000000 I
1J
b00000000000000000000000000000000 N
b00000000000000000000000000000000 O
b00000000000000000000000000001100 Q
b00000000000001011000010100010011 R
b00000000000000000000000011111000 S
1T
0V
b0010011 W
b00000 Y
b01010 Z
#56
0J
#57
b00000000000000000000000000000001 &
b00000000000000000000000000010100 '
b00000000000000000000000000010001 (
b00000000000000000000000011111000 3
b000000000001 I
1J
b00000000000000000000000011111000 L
b00000000000000000000000000000001 O
b00000000000000000000000000010000 Q
b00000000000101011000010110010011 R
b00000000000000000000000011111001 S
b00001 Y
b01011 Z
#58
0J
#59
b111 $
b011 %
b00000000000000000000000011111111 &
b00000000000000000000000000001100 '
b00000000000000000000000000001100 (
b00000000000000000000000011111001 4
b111111111000 I
1J
b00000000000000000000000011111001 M
b00000000000000000000000011111111 N
b11111111111111111111111111111000 O
b00000000000000000000000000010100 Q
b11111110011001011001100011100011 R
b00000000000000000000000000000000 S
0T
1V
b1100011 W
b00110 Y
b10001 Z
#60
0J
#61
b000 $
b000 %
b00000000000000000000000000000000 &
b00000000000000000000000000010000 '
b000000000000 I
1J
b00000000000000000000000000000000 N
b00000000000000000000000000000000 O
b00000000000000000000000000001100 Q
b00000000000001011000010100010011 R
b00000000000000000000000011111001 S
1T
0V
b0010011 W
b00000 Y
b01010 Z
#62
0J
#63
b00000000000000000000000000000001 &
b00000000000000000000000000010100 '
b00000000000000000000000000010001 (
b00000000000000000000000011111001 3
b000000000001 I
1J
b00000000000000000000000011111001 L
b00000000000000000000000000000001 O
b00000000000000000000000000010000 Q
b00000000000101011000010110010011 R
b00000000000000000000000011111010 S
b00001 Y
b01011 Z
#64
0J
#65
b111 $
b011 %
b00000000000000000000000011111111 &
b00000000000000000000000000001100 '
b00000000000000000000000000001100 (
b00000000000000000000000011111010 4
b111111111000 I
1J
b00000000000000000000000011111010 M
b00000000000000000000000011111111 N
b11111111111111111111111111111000 O
b00000000000000000000000000010100 Q
b11111110011001011001100011100011 R
b00000000000000000000000000000000 S
0T
1V
b1100011 W
b00110 Y
b10001 Z
#66
0J
#67
b000 $
b000 %
b00000000000000000000000000000000 &
b00000000000000000000000000010000 '
b000000000000 I
1J
b00000000000000000000000000000000 N
b00000000000000000000000000000000 O
b00000000000000000000000000001100 Q
b00000000000001011000010100010011 R
b00000000000000000000000011111010 S
1T
0V
b0010011 W
b00000 Y
b01010 Z
#68
0J
#69
b00000000000000000000000000000001 &
b00000000000000000000000000010100 '
b00000000000000000000000000010001 (
b00000000000000000000000011111010 3
b000000000001 I
1J
b00000000000000000000000011111010 L
b00000000000000000000000000000001 O
b00000000000000000000000000010000 Q
b00000000000101011000010110010011 R
b00000000000000000000000011111011 S
b00001 Y
b01011 Z
#70
0J
#71
b111 $
b011 %
b00000000000000000000000011111111 &
b00000000000000000000000000001100 '
b00000000000000000000000000001100 (
b00000000000000000000000011111011 4
b111111111000 I
1J
b00000000000000000000000011111011 M
b00000000000000000000000011111111 N
b11111111111111111111111111111000 O
b00000000000000000000000000010100 Q
b11111110011001011001100011100011 R
b00000000000000000000000000000000 S
0T
1V
b1100011 W
b00110 Y
b10001 Z
#72
0J
#73
b000 $
b000 %
b00000000000000000000000000000000 &
b00000000000000000000000000010000 '
b000000000000 I
1J
b00000000000000000000000000000000 N
b00000000000000000000000000000000 O
b00000000000000000000000000001100 Q
b00000000000001011000010100010011 R
b00000000000000000000000011111011 S
1T
0V
b0010011 W
b00000 Y
b01010 Z
#74
0J
#75
b00000000000000000000000000000001 &
b00000000000000000000000000010100 '
b00000000000000000000000000010001 (
b00000000000000000000000011111011 3
b000000000001 I
1J
b00000000000000000000000011111011 L
b00000000000000000000000000000001 O
b00000000000000000000000000010000 Q
b00000000000101011000010110010011 R
b00000000000000000000000011111100 S
b00001 Y
b01011 Z
#76
0J
#77
b111 $
b011 %
b00000000000000000000000011111111 &
b00000000000000000000000000001100 '
b00000000000000000000000000001100 (
b00000000000000000000000011111100 4
b111111111000 I
1J
b00000000000000000000000011111100 M
b00000000000000000000000011111111 N
b11111111111111111111111111111000 O
b00000000000000000000000000010100 Q
b11111110011001011001100011100011 R
b00000000000000000000000000000000 S
0T
1V
b1100011 W
b00110 Y
b10001 Z
#78
0J
#79
b000 $
b000 %
b00000000000000000000000000000000 &
b00000000000000000000000000010000 '
b000000000000 I
1J
b00000000000000000000000000000000 N
b00000000000000000000000000000000 O
b00000000000000000000000000001100 Q
b00000000000001011000010100010011 R
b00000000000000000000000011111100 S
1T
0V
b0010011 W
b00000 Y
b01010 Z
#80
0J
#81
b00000000000000000000000000000001 &
b00000000000000000000000000010100 '
b00000000000000000000000000010001 (
b00000000000000000000000011111100 3
b000000000001 I
1J
b00000000000000000000000011111100 L
b00000000000000000000000000000001 O
b00000000000000000000000000010000 Q
b00000000000101011000010110010011 R
b00000000000000000000000011111101 S
b00001 Y
b01011 Z
#82
0J
#83
b111 $
b011 %
b00000000000000000000000011111111 &
b00000000000000000000000000001100 '
b00000000000000000000000000001100 (
b00000000000000000000000011111101 4
b111111111000 I
1J
b00000000000000000000000011111101 M
b00000000000000000000000011111111 N
b11111111111111111111111111111000 O
b00000000000000000000000000010100 Q
b11111110011001011001100011100011 R
b00000000000000000000000000000000 S
0T
1V
b1100011 W
b00110 Y
b10001 Z
#84
0J
#85
b000 $
b000 %
b00000000000000000000000000000000 &
b00000000000000000000000000010000 '
b000000000000 I
1J
b00000000000000000000000000000000 N
b00000000000000000000000000000000 O
b00000000000000000000000000001100 Q
b00000000000001011000010100010011 R
b00000000000000000000000011111101 S
1T
0V
b0010011 W
b00000 Y
b01010 Z
#86
0J
#87
b00000000000000000000000000000001 &
b00000000000000000000000000010100 '
b00000000000000000000000000010001 (
b00000000000000000000000011111101 3
b000000000001 I
1J
b00000000000000000000000011111101 L
b00000000000000000000000000000001 O
b00000000000000000000000000010000 Q
b00000000000101011000010110010011 R
b00000000000000000000000011111110 S
b00001 Y
b01011 Z
#88
0J
#89
b111 $
b011 %
b00000000000000000000000011111111 &
b00000000000000000000000000001100 '
b00000000000000000000000000001100 (
b00000000000000000000000011111110 4
b111111111000 I
1J
b00000000000000000000000011111110 M
b00000000000000000000000011111111 N
b11111111111111111111111111111000 O
b00000000000000000000000000010100 Q
b11111110011001011001100011100011 R
b00000000000000000000000000000000 S
0T
1V
b1100011 W
b00110 Y
b10001 Z
#90
0J
#91
b000 $
b000 %
b00000000000000000000000000000000 &
b00000000000000000000000000010000 '
b000000000000 I
1J
b00000000000000000000000000000000 N
b00000000000000000000000000000000 O
b00000000000000000000000000001100 Q
b00000000000001011000010100010011 R
b00000000000000000000000011111110 S
1T
0V
b0010011 W
b00000 Y
b01010 Z
#92
0J
#93
b00000000000000000000000000000001 &
b00000000000000000000000000010100 '
b00000000000000000000000000010001 (
b00000000000000000000000011111110 3
b000000000001 I
1J
b00000000000000000000000011111110 L
b00000000000000000000000000000001 O
b00000000000000000000000000010000 Q
b00000000000101011000010110010011 R
b00000000000000000000000011111111 S
b00001 Y
b01011 Z
#94
0J
#95
b111 $
b011 %
b00000000000000000000000011111111 &
b00000000000000000000000000011000 '
b00000000000000000000000000001100 (
b00000000000000000000000011111111 4
b111111111000 I
1J
b00000000000000000000000011111111 M
b00000000000000000000000011111111 N
b11111111111111111111111111111000 O
b00000000000000000000000000010100 Q
b11111110011001011001100011100011 R
b00000000000000000000000000000000 S
0T
1U
b1100011 W
b00110 Y
b10001 Z
#96
0J
#97
b00000000000000000000000000000000 &
b00000000000000000000000000001000 '
b00000000000000000000000000001000 (
b111111110000 I
1J
b00000000000000000000000000000000 N
b11111111111111111111111111110000 O
b00110 P
b00000000000000000000000000011000 Q
b11111110000000110001000011100011 R
0U
1V
b00110 X
b00000 Y
b00001 Z
#98
0J
