Debugged_cpu/rf.sv
module rf #(
    parameter  A_WIDTH = 5,
                D_WIDTH = 32
) (
    input logic clk,
    input logic we3,
    input logic [A_WIDTH-1:0] ad1,
    input logic [A_WIDTH-1:0] ad2,
    input logic [A_WIDTH-1:0] ad3,
    input logic [D_WIDTH-1:0] wd3,
    output logic [D_WIDTH-1:0] a0,
    output logic [D_WIDTH-1:0] rd1,
    output logic [D_WIDTH-1:0] rd2
);

    logic [D_WIDTH-1:0] rf_array [2**A_WIDTH-1:0];

    always_comb begin
        rd1 = rf_array[ad1];
        rd2 = rf_array[ad2];
    end

    initial begin
        for (int i = 0; i < $size(rf_array); i++) begin
            rf_array[i] = 32'b0;
        end
    end

    always_ff @(posedge clk) begin
        if(we3) rf_array[ad3] <= wd3; 
    end
    
    assign a0 = rf_array[10];
endmodule

Debugged_cpu/alu.sv
module alu #(
    parameter D_WIDTH = 32
)(
    input logic alusrc,
    input logic [2:0] aluctrl,
    input logic [D_WIDTH-1:0] aluop1,
    input logic [D_WIDTH-1:0] immop,
    input logic [D_WIDTH-1:0] regop2,
    output logic [D_WIDTH-1:0] aluout,
    output logic eq,
    output logic [D_WIDTH-1:0] aluop2
);

    assign aluop2 = alusrc ? immop : regop2;

    always_comb begin
        case (aluctrl)
            3'b000: aluout = aluop1 + aluop2;
            3'b001: aluout = 32'b0;
            3'b010: aluout = 32'b0;
            3'b011: aluout = 32'b0;
            3'b100: aluout = 32'b0;
            3'b101: aluout = 32'b0;
            3'b110: aluout = 32'b0;
            default: aluout = 0;
        endcase
    end


    assign eq = (aluop1 == aluop2);

    
endmodule

omar/RISC-V-1/temp completed/signextender.sv
module signextender(
    input logic [31:0] instruction,
    input logic [2:0] immsrc,
    output logic [31:0] immop
);
    logic [11:0] uimm;
    
    always_comb begin
        case (immsrc)    
            3'b000: uimm = instruction[31:20]; // immediate
            // 3'b001: uimm = instruction[31:12]; // upper immediate
            // 3'b010: uimm = {instruction[31:25], instruction[11:7]}; // store
            3'b011: uimm = {instruction[31], instruction[7], instruction[30:25], instruction[11:8]}; // branch
            // 3'b100: uimm = {instruction[31], instruction[19:12], instruction[20], instruction[30:21]}; // jump
            default: uimm = 12'b0;
        endcase
    end

    // for now this will work, however for upper immediate and jump a case will be required
    assign immop = {{5'd20{uimm[11]}}, uimm[11:0]};
    
endmodule

Debugged_cpu/instrmem.sv
module instrmem #(
    parameter   A_WIDTH = 32,
                D_WIDTH = 8        
) (
    input [A_WIDTH-1:0] address,
    output [31:0] dout
);
    logic [D_WIDTH-1:0] rom_array [2000:0];
    
    initial begin 
        $display("Loading rom.");
        $readmemh("program.hex", rom_array);
        $display("Program written to ROM successfully");
    end;

    assign dout = {{rom_array[address]}, {rom_array[address+1]}, {rom_array[address+2]}, {rom_array[address+3]}}; 

endmodule

omar/RISC-V-1/temp completed/pcountunit.sv

module pcountunit #(
    parameter WIDTH = 32
) (
    input logic pcsrc,
    input logic clk,
    input logic rst,
    input logic [WIDTH-1:0] immop,
    output logic [WIDTH-1:0] pc
);

    logic [WIDTH-1:0] next_pc;
    logic [WIDTH-1:0] branch_pc;
    
    always_comb begin
        branch_pc = pc + immop;
        next_pc = pcsrc ? branch_pc : pc + 4;    
    end

    always_ff @(posedge clk) begin
        if(rst) pc <= 32'b0;
        else pc <= next_pc;
    end



endmodule

Debugged_cpu/controlunit.sv
module controlunit(
    input logic [31:0] instruction,
    input logic eq,
    output logic regwrite,
    output logic [2:0] aluctrl,
    output logic alusrc,
    output logic pcsrc,
    output logic [2:0] immsrc
);
    logic [6:0] opcode;
    assign opcode = instruction[6:0];

    always_comb begin
        case (opcode)
            7'd19: begin
                aluctrl = instruction[14:12];
                alusrc = 1'b1;
                regwrite = 1'b1;
                immsrc = 3'b000;
                pcsrc = 1'b0;
            end
            7'd99:begin
                aluctrl = 3'b111;
                alusrc = 1'b0;
                regwrite = 1'b0;
                immsrc = 3'b011;
                pcsrc = !eq;
            end
            default: begin
                aluctrl = 3'b0;
                alusrc = 1'b0;
                regwrite = 1'b0;
                immsrc = 3'b0;
                pcsrc = 1'b1;
            end
        endcase
    end
    
    
endmodule

omar/cpu.sv
module cpu #(
    parameter WIDTH = 32
) (
    input logic clk, 
    input logic rst,
    output logic [WIDTH-1:0] a0_output,
    output logic [WIDTH-1:0] rf_dout1,
    output logic [WIDTH-1:0] rf_dout2,
    output logic [WIDTH-1:0] interm_immop,
    output logic [4:0] rd_add,
    output logic [WIDTH-1:0] prog_addr,
    logic [WIDTH-1:0] interm_ins,
    logic [WIDTH-1:0] aluop2_test

);

logic [WIDTH-1:0] rf_din;
logic [2:0] interm_aluctrl;
logic [2:0] interm_immsrc;
logic interm_alusrc;
logic interm_eq;
logic interm_pcsrc;
logic write_en;

assign rd_add = interm_ins[19:15];

controlunit ctrlunit(
    .instruction(interm_ins), //in
    .eq(interm_eq), //in
    .regwrite(write_en), //out
    .aluctrl(interm_aluctrl), //out
    .alusrc(interm_alusrc), //out
    .pcsrc(interm_pcsrc), //out
    .immsrc(interm_immsrc) //out
);

pcountunit programcounter(
    .clk(clk), //in
    .rst(rst), //in
    .pcsrc(interm_pcsrc), //in
    .immop(interm_immop), //in
    .pc(prog_addr) //out
);

instrmem programmem(
    .address(prog_addr),
    .dout(interm_ins)
);

signextender sgnextend(
    .instruction(interm_ins),
    .immsrc(interm_immsrc),
    .immop(interm_immop)
);


alu alu(
    .alusrc(interm_alusrc),
    .aluctrl(interm_aluctrl),
    .aluop1(rf_dout1),
    .immop(interm_immop),
    .regop2(rf_dout2),
    .aluout(rf_din),
    .eq(interm_eq),
    .aluop2(aluop2_test)
);

rf registerfile(
    .clk(clk), //in
    .we3(write_en), //in
    .ad1(interm_ins[19:15]), //in
    .ad2(interm_ins[24:20]), //in
    .ad3(interm_ins[11:7]), //in
    .wd3(rf_din), //in
    .a0(a0_output), //out
    .rd1(rf_dout1), //out
    .rd2(rf_dout2) //out
);



endmodule

Debugged_cpu/cpu.vcd
$version Generated by VerilatedVcd $end
$date Thu Nov 24 18:45:26 2022 $end
$timescale 1ps $end

 $scope module TOP $end
  $var wire 32 N a0_output [31:0] $end
  $var wire 32 U aluop2_test [31:0] $end
  $var wire  1 L clk $end
  $var wire 32 Q interm_immop [31:0] $end
  $var wire 32 T interm_ins [31:0] $end
  $var wire 32 S prog_addr [31:0] $end
  $var wire  5 R rd_add [4:0] $end
  $var wire 32 O rf_dout1 [31:0] $end
  $var wire 32 P rf_dout2 [31:0] $end
  $var wire  1 M rst $end
  $scope module cpu $end
   $var wire 32 ] WIDTH [31:0] $end
   $var wire 32 N a0_output [31:0] $end
   $var wire 32 U aluop2_test [31:0] $end
   $var wire  1 L clk $end
   $var wire  3 D interm_aluctrl [2:0] $end
   $var wire  1 F interm_alusrc $end
   $var wire  1 G interm_eq $end
   $var wire 32 Q interm_immop [31:0] $end
   $var wire  3 E interm_immsrc [2:0] $end
   $var wire 32 T interm_ins [31:0] $end
   $var wire  1 W interm_pcsrc $end
   $var wire 32 S prog_addr [31:0] $end
   $var wire  5 R rd_add [4:0] $end
   $var wire 32 V rf_din [31:0] $end
   $var wire 32 O rf_dout1 [31:0] $end
   $var wire 32 P rf_dout2 [31:0] $end
   $var wire  1 M rst $end
   $var wire  1 H write_en $end
   $scope module alu $end
    $var wire 32 ] D_WIDTH [31:0] $end
    $var wire  3 D aluctrl [2:0] $end
    $var wire 32 O aluop1 [31:0] $end
    $var wire 32 U aluop2 [31:0] $end
    $var wire 32 V aluout [31:0] $end
    $var wire  1 F alusrc $end
    $var wire  1 G eq $end
    $var wire 32 Q immop [31:0] $end
    $var wire 32 P regop2 [31:0] $end
   $upscope $end
   $scope module ctrlunit $end
    $var wire  3 D aluctrl [2:0] $end
    $var wire  1 F alusrc $end
    $var wire  1 G eq $end
    $var wire  3 E immsrc [2:0] $end
    $var wire 32 T instruction [31:0] $end
    $var wire  7 X opcode [6:0] $end
    $var wire  1 W pcsrc $end
    $var wire  1 H regwrite $end
   $upscope $end
   $scope module programcounter $end
    $var wire 32 ] WIDTH [31:0] $end
    $var wire 32 J branch_pc [31:0] $end
    $var wire  1 L clk $end
    $var wire 32 Q immop [31:0] $end
    $var wire 32 I next_pc [31:0] $end
    $var wire 32 S pc [31:0] $end
    $var wire  1 W pcsrc $end
    $var wire  1 M rst $end
   $upscope $end
   $scope module programmem $end
    $var wire 32 ^ A_WIDTH [31:0] $end
    $var wire 32 _ D_WIDTH [31:0] $end
    $var wire 20 Y address [19:0] $end
    $var wire 32 T dout [31:0] $end
   $upscope $end
   $scope module registerfile $end
    $var wire 32 ` A_WIDTH [31:0] $end
    $var wire 32 ] D_WIDTH [31:0] $end
    $var wire 32 N a0 [31:0] $end
    $var wire  5 Z ad1 [4:0] $end
    $var wire  5 [ ad2 [4:0] $end
    $var wire  5 \ ad3 [4:0] $end
    $var wire  1 L clk $end
    $var wire 32 O rd1 [31:0] $end
    $var wire 32 P rd2 [31:0] $end
    $var wire 32 $ rf_array[0] [31:0] $end
    $var wire 32 . rf_array[10] [31:0] $end
    $var wire 32 / rf_array[11] [31:0] $end
    $var wire 32 0 rf_array[12] [31:0] $end
    $var wire 32 1 rf_array[13] [31:0] $end
    $var wire 32 2 rf_array[14] [31:0] $end
    $var wire 32 3 rf_array[15] [31:0] $end
    $var wire 32 4 rf_array[16] [31:0] $end
    $var wire 32 5 rf_array[17] [31:0] $end
    $var wire 32 6 rf_array[18] [31:0] $end
    $var wire 32 7 rf_array[19] [31:0] $end
    $var wire 32 % rf_array[1] [31:0] $end
    $var wire 32 8 rf_array[20] [31:0] $end
    $var wire 32 9 rf_array[21] [31:0] $end
    $var wire 32 : rf_array[22] [31:0] $end
    $var wire 32 ; rf_array[23] [31:0] $end
    $var wire 32 < rf_array[24] [31:0] $end
    $var wire 32 = rf_array[25] [31:0] $end
    $var wire 32 > rf_array[26] [31:0] $end
    $var wire 32 ? rf_array[27] [31:0] $end
    $var wire 32 @ rf_array[28] [31:0] $end
    $var wire 32 A rf_array[29] [31:0] $end
    $var wire 32 & rf_array[2] [31:0] $end
    $var wire 32 B rf_array[30] [31:0] $end
    $var wire 32 C rf_array[31] [31:0] $end
    $var wire 32 ' rf_array[3] [31:0] $end
    $var wire 32 ( rf_array[4] [31:0] $end
    $var wire 32 ) rf_array[5] [31:0] $end
    $var wire 32 * rf_array[6] [31:0] $end
    $var wire 32 + rf_array[7] [31:0] $end
    $var wire 32 , rf_array[8] [31:0] $end
    $var wire 32 - rf_array[9] [31:0] $end
    $var wire 32 V wd3 [31:0] $end
    $var wire  1 H we3 $end
    $scope module unnamedblk1 $end
     $var wire 32 # i [31:0] $end
    $upscope $end
   $upscope $end
   $scope module sgnextend $end
    $var wire 32 Q immop [31:0] $end
    $var wire  3 E immsrc [2:0] $end
    $var wire 32 T instruction [31:0] $end
    $var wire 12 K uimm [11:0] $end
   $upscope $end
  $upscope $end
 $upscope $end
$enddefinitions $end


#0
b00000000000000000000000000000000 #
b00000000000000000000000000000000 $
b00000000000000000000000000000000 %
b00000000000000000000000000000000 &
b00000000000000000000000000000000 '
b00000000000000000000000000000000 (
b00000000000000000000000000000000 )
b00000000000000000000000000000000 *
b00000000000000000000000000000000 +
b00000000000000000000000000000000 ,
b00000000000000000000000000000000 -
b00000000000000000000000000000000 .
b00000000000000000000000000000000 /
b00000000000000000000000000000000 0
b00000000000000000000000000000000 1
b00000000000000000000000000000000 2
b00000000000000000000000000000000 3
b00000000000000000000000000000000 4
b00000000000000000000000000000000 5
b00000000000000000000000000000000 6
b00000000000000000000000000000000 7
b00000000000000000000000000000000 8
b00000000000000000000000000000000 9
b00000000000000000000000000000000 :
b00000000000000000000000000000000 ;
b00000000000000000000000000000000 <
b00000000000000000000000000000000 =
b00000000000000000000000000000000 >
b00000000000000000000000000000000 ?
b00000000000000000000000000000000 @
b00000000000000000000000000000000 A
b00000000000000000000000000000000 B
b00000000000000000000000000000000 C
b000 D
b000 E
0F
0G
0H
b00000000000000000000000000000000 I
b00000000000000000000000000000000 J
b000000000000 K
0L
0M
b00000000000000000000000000000000 N
b00000000000000000000000000000000 O
b00000000000000000000000000000000 P
b00000000000000000000000000000000 Q
b00000 R
b00000000000000000000000000000000 S
b00000000000000000000000000000000 T
b00000000000000000000000000000000 U
b00000000000000000000000000000000 V
1W
b0000000 X
b00000000000000000000 Y
b00000 Z
b00000 [
b00000 \
b00000000000000000000000000100000 ]
b00000000000000000000000000010100 ^
b00000000000000000000000000001000 _
b00000000000000000000000000000101 `
#1
b00000000000000000000000000100000 #
1F
1H
b00000000000000000000000000000100 I
b00000000000000000000000011111111 J
b000011111111 K
1L
b00000000000000000000000011111111 Q
b00001111111100000000001100010011 T
b00000000000000000000000011111111 U
b00000000000000000000000011111111 V
0W
b0010011 X
b11111 [
b00110 \
#2
0L
#3
b00000000000000000000000011111111 *
1G
b00000000000000000000000000001000 I
b00000000000000000000000000000100 J
b000000000000 K
1L
b00000000000000000000000000000000 Q
b00000000000000000000000000000100 S
b00000000000000000000010100010011 T
b00000000000000000000000000000000 U
b00000000000000000000000000000000 V
b00000000000000000100 Y
b00000 [
b01010 \
#4
0L
#5
0G
b00000000000000000000000000001100 I
b00000000000000000000000011111000 J
b000011110000 K
1L
b00000000000000000000000011110000 Q
b00000000000000000000000000001000 S
b00001111000000000000010110010011 T
b00000000000000000000000011110000 U
b00000000000000000000000011110000 V
b00000000000000001000 Y
b10000 [
b01011 \
#6
0L
#7
b00000000000000000000000011110000 /
b00000000000000000000000000010000 I
b00000000000000000000000000001100 J
b000000000000 K
1L
b00000000000000000000000011110000 O
b00000000000000000000000000000000 Q
b01011 R
b00000000000000000000000000001100 S
b00000000000001011000010100010011 T
b00000000000000000000000000000000 U
b00000000000000001100 Y
b01011 Z
b00000 [
b01010 \
#8
0L
#9
b00000000000000000000000011110000 .
b00000000000000000000000000010100 I
b00000000000000000000000000010001 J
b000000000001 K
1L
b00000000000000000000000011110000 N
b00000000000000000000000000000001 Q
b00000000000000000000000000010000 S
b00000000000101011000010110010011 T
b00000000000000000000000000000001 U
b00000000000000000000000011110001 V
b00000000000000010000 Y
b00001 [
b01011 \
#10
0L
#11
b00000000000000000000000011110001 /
b111 D
b011 E
0F
0H
b00000000000000000000000000001100 I
b00000000000000000000000000001100 J
b111111111000 K
1L
b00000000000000000000000011110001 O
b00000000000000000000000011111111 P
b11111111111111111111111111111000 Q
b00000000000000000000000000010100 S
b11111110011001011001100011100011 T
b00000000000000000000000011111111 U
b00000000000000000000000000000000 V
1W
b1100011 X
b00000000000000010100 Y
b00110 [
b10001 \
#12
0L
#13
b000 D
b000 E
1F
1H
b00000000000000000000000000010000 I
b000000000000 K
1L
b00000000000000000000000000000000 P
b00000000000000000000000000000000 Q
b00000000000000000000000000001100 S
b00000000000001011000010100010011 T
b00000000000000000000000000000000 U
b00000000000000000000000011110001 V
0W
b0010011 X
b00000000000000001100 Y
b00000 [
b01010 \
#14
0L
#15
b00000000000000000000000011110001 .
b00000000000000000000000000010100 I
b00000000000000000000000000010001 J
b000000000001 K
1L
b00000000000000000000000011110001 N
b00000000000000000000000000000001 Q
b00000000000000000000000000010000 S
b00000000000101011000010110010011 T
b00000000000000000000000000000001 U
b00000000000000000000000011110010 V
b00000000000000010000 Y
b00001 [
b01011 \
#16
0L
#17
b00000000000000000000000011110010 /
b111 D
b011 E
0F
0H
b00000000000000000000000000001100 I
b00000000000000000000000000001100 J
b111111111000 K
1L
b00000000000000000000000011110010 O
b00000000000000000000000011111111 P
b11111111111111111111111111111000 Q
b00000000000000000000000000010100 S
b11111110011001011001100011100011 T
b00000000000000000000000011111111 U
b00000000000000000000000000000000 V
1W
b1100011 X
b00000000000000010100 Y
b00110 [
b10001 \
#18
0L
#19
b000 D
b000 E
1F
1H
b00000000000000000000000000010000 I
b000000000000 K
1L
b00000000000000000000000000000000 P
b00000000000000000000000000000000 Q
b00000000000000000000000000001100 S
b00000000000001011000010100010011 T
b00000000000000000000000000000000 U
b00000000000000000000000011110010 V
0W
b0010011 X
b00000000000000001100 Y
b00000 [
b01010 \
#20
0L
#21
b00000000000000000000000011110010 .
b00000000000000000000000000010100 I
b00000000000000000000000000010001 J
b000000000001 K
1L
b00000000000000000000000011110010 N
b00000000000000000000000000000001 Q
b00000000000000000000000000010000 S
b00000000000101011000010110010011 T
b00000000000000000000000000000001 U
b00000000000000000000000011110011 V
b00000000000000010000 Y
b00001 [
b01011 \
#22
0L
#23
b00000000000000000000000011110011 /
b111 D
b011 E
0F
0H
b00000000000000000000000000001100 I
b00000000000000000000000000001100 J
b111111111000 K
1L
b00000000000000000000000011110011 O
b00000000000000000000000011111111 P
b11111111111111111111111111111000 Q
b00000000000000000000000000010100 S
b11111110011001011001100011100011 T
b00000000000000000000000011111111 U
b00000000000000000000000000000000 V
1W
b1100011 X
b00000000000000010100 Y
b00110 [
b10001 \
#24
0L
#25
b000 D
b000 E
1F
1H
b00000000000000000000000000010000 I
b000000000000 K
1L
b00000000000000000000000000000000 P
b00000000000000000000000000000000 Q
b00000000000000000000000000001100 S
b00000000000001011000010100010011 T
b00000000000000000000000000000000 U
b00000000000000000000000011110011 V
0W
b0010011 X
b00000000000000001100 Y
b00000 [
b01010 \
#26
0L
#27
b00000000000000000000000011110011 .
b00000000000000000000000000010100 I
b00000000000000000000000000010001 J
b000000000001 K
1L
b00000000000000000000000011110011 N
b00000000000000000000000000000001 Q
b00000000000000000000000000010000 S
b00000000000101011000010110010011 T
b00000000000000000000000000000001 U
b00000000000000000000000011110100 V
b00000000000000010000 Y
b00001 [
b01011 \
#28
0L
#29
b00000000000000000000000011110100 /
b111 D
b011 E
0F
0H
b00000000000000000000000000001100 I
b00000000000000000000000000001100 J
b111111111000 K
1L
b00000000000000000000000011110100 O
b00000000000000000000000011111111 P
b11111111111111111111111111111000 Q
b00000000000000000000000000010100 S
b11111110011001011001100011100011 T
b00000000000000000000000011111111 U
b00000000000000000000000000000000 V
1W
b1100011 X
b00000000000000010100 Y
b00110 [
b10001 \
#30
0L
#31
b000 D
b000 E
1F
1H
b00000000000000000000000000010000 I
b000000000000 K
1L
b00000000000000000000000000000000 P
b00000000000000000000000000000000 Q
b00000000000000000000000000001100 S
b00000000000001011000010100010011 T
b00000000000000000000000000000000 U
b00000000000000000000000011110100 V
0W
b0010011 X
b00000000000000001100 Y
b00000 [
b01010 \
#32
0L
#33
b00000000000000000000000011110100 .
b00000000000000000000000000010100 I
b00000000000000000000000000010001 J
b000000000001 K
1L
b00000000000000000000000011110100 N
b00000000000000000000000000000001 Q
b00000000000000000000000000010000 S
b00000000000101011000010110010011 T
b00000000000000000000000000000001 U
b00000000000000000000000011110101 V
b00000000000000010000 Y
b00001 [
b01011 \
#34
0L
#35
b00000000000000000000000011110101 /
b111 D
b011 E
0F
0H
b00000000000000000000000000001100 I
b00000000000000000000000000001100 J
b111111111000 K
1L
b00000000000000000000000011110101 O
b00000000000000000000000011111111 P
b11111111111111111111111111111000 Q
b00000000000000000000000000010100 S
b11111110011001011001100011100011 T
b00000000000000000000000011111111 U
b00000000000000000000000000000000 V
1W
b1100011 X
b00000000000000010100 Y
b00110 [
b10001 \
#36
0L
#37
b000 D
b000 E
1F
1H
b00000000000000000000000000010000 I
b000000000000 K
1L
b00000000000000000000000000000000 P
b00000000000000000000000000000000 Q
b00000000000000000000000000001100 S
b00000000000001011000010100010011 T
b00000000000000000000000000000000 U
b00000000000000000000000011110101 V
0W
b0010011 X
b00000000000000001100 Y
b00000 [
b01010 \
#38
0L
#39
b00000000000000000000000011110101 .
b00000000000000000000000000010100 I
b00000000000000000000000000010001 J
b000000000001 K
1L
b00000000000000000000000011110101 N
b00000000000000000000000000000001 Q
b00000000000000000000000000010000 S
b00000000000101011000010110010011 T
b00000000000000000000000000000001 U
b00000000000000000000000011110110 V
b00000000000000010000 Y
b00001 [
b01011 \
#40
0L
#41
b00000000000000000000000011110110 /
b111 D
b011 E
0F
0H
b00000000000000000000000000001100 I
b00000000000000000000000000001100 J
b111111111000 K
1L
b00000000000000000000000011110110 O
b00000000000000000000000011111111 P
b11111111111111111111111111111000 Q
b00000000000000000000000000010100 S
b11111110011001011001100011100011 T
b00000000000000000000000011111111 U
b00000000000000000000000000000000 V
1W
b1100011 X
b00000000000000010100 Y
b00110 [
b10001 \
#42
0L
#43
b000 D
b000 E
1F
1H
b00000000000000000000000000010000 I
b000000000000 K
1L
b00000000000000000000000000000000 P
b00000000000000000000000000000000 Q
b00000000000000000000000000001100 S
b00000000000001011000010100010011 T
b00000000000000000000000000000000 U
b00000000000000000000000011110110 V
0W
b0010011 X
b00000000000000001100 Y
b00000 [
b01010 \
#44
0L
#45
b00000000000000000000000011110110 .
b00000000000000000000000000010100 I
b00000000000000000000000000010001 J
b000000000001 K
1L
b00000000000000000000000011110110 N
b00000000000000000000000000000001 Q
b00000000000000000000000000010000 S
b00000000000101011000010110010011 T
b00000000000000000000000000000001 U
b00000000000000000000000011110111 V
b00000000000000010000 Y
b00001 [
b01011 \
#46
0L
#47
b00000000000000000000000011110111 /
b111 D
b011 E
0F
0H
b00000000000000000000000000001100 I
b00000000000000000000000000001100 J
b111111111000 K
1L
b00000000000000000000000011110111 O
b00000000000000000000000011111111 P
b11111111111111111111111111111000 Q
b00000000000000000000000000010100 S
b11111110011001011001100011100011 T
b00000000000000000000000011111111 U
b00000000000000000000000000000000 V
1W
b1100011 X
b00000000000000010100 Y
b00110 [
b10001 \
#48
0L
#49
b000 D
b000 E
1F
1H
b00000000000000000000000000010000 I
b000000000000 K
1L
b00000000000000000000000000000000 P
b00000000000000000000000000000000 Q
b00000000000000000000000000001100 S
b00000000000001011000010100010011 T
b00000000000000000000000000000000 U
b00000000000000000000000011110111 V
0W
b0010011 X
b00000000000000001100 Y
b00000 [
b01010 \
#50
0L
#51
b00000000000000000000000011110111 .
b00000000000000000000000000010100 I
b00000000000000000000000000010001 J
b000000000001 K
1L
b00000000000000000000000011110111 N
b00000000000000000000000000000001 Q
b00000000000000000000000000010000 S
b00000000000101011000010110010011 T
b00000000000000000000000000000001 U
b00000000000000000000000011111000 V
b00000000000000010000 Y
b00001 [
b01011 \
#52
0L
#53
b00000000000000000000000011111000 /
b111 D
b011 E
0F
0H
b00000000000000000000000000001100 I
b00000000000000000000000000001100 J
b111111111000 K
1L
b00000000000000000000000011111000 O
b00000000000000000000000011111111 P
b11111111111111111111111111111000 Q
b00000000000000000000000000010100 S
b11111110011001011001100011100011 T
b00000000000000000000000011111111 U
b00000000000000000000000000000000 V
1W
b1100011 X
b00000000000000010100 Y
b00110 [
b10001 \
#54
0L
#55
b000 D
b000 E
1F
1H
b00000000000000000000000000010000 I
b000000000000 K
1L
b00000000000000000000000000000000 P
b00000000000000000000000000000000 Q
b00000000000000000000000000001100 S
b00000000000001011000010100010011 T
b00000000000000000000000000000000 U
b00000000000000000000000011111000 V
0W
b0010011 X
b00000000000000001100 Y
b00000 [
b01010 \
#56
0L
#57
b00000000000000000000000011111000 .
b00000000000000000000000000010100 I
b00000000000000000000000000010001 J
b000000000001 K
1L
b00000000000000000000000011111000 N
b00000000000000000000000000000001 Q
b00000000000000000000000000010000 S
b00000000000101011000010110010011 T
b00000000000000000000000000000001 U
b00000000000000000000000011111001 V
b00000000000000010000 Y
b00001 [
b01011 \
#58
0L
#59
b00000000000000000000000011111001 /
b111 D
b011 E
0F
0H
b00000000000000000000000000001100 I
b00000000000000000000000000001100 J
b111111111000 K
1L
b00000000000000000000000011111001 O
b00000000000000000000000011111111 P
b11111111111111111111111111111000 Q
b00000000000000000000000000010100 S
b11111110011001011001100011100011 T
b00000000000000000000000011111111 U
b00000000000000000000000000000000 V
1W
b1100011 X
b00000000000000010100 Y
b00110 [
b10001 \
#60
0L
#61
b000 D
b000 E
1F
1H
b00000000000000000000000000010000 I
b000000000000 K
1L
b00000000000000000000000000000000 P
b00000000000000000000000000000000 Q
b00000000000000000000000000001100 S
b00000000000001011000010100010011 T
b00000000000000000000000000000000 U
b00000000000000000000000011111001 V
0W
b0010011 X
b00000000000000001100 Y
b00000 [
b01010 \
#62
0L
#63
b00000000000000000000000011111001 .
b00000000000000000000000000010100 I
b00000000000000000000000000010001 J
b000000000001 K
1L
b00000000000000000000000011111001 N
b00000000000000000000000000000001 Q
b00000000000000000000000000010000 S
b00000000000101011000010110010011 T
b00000000000000000000000000000001 U
b00000000000000000000000011111010 V
b00000000000000010000 Y
b00001 [
b01011 \
#64
0L
#65
b00000000000000000000000011111010 /
b111 D
b011 E
0F
0H
b00000000000000000000000000001100 I
b00000000000000000000000000001100 J
b111111111000 K
1L
b00000000000000000000000011111010 O
b00000000000000000000000011111111 P
b11111111111111111111111111111000 Q
b00000000000000000000000000010100 S
b11111110011001011001100011100011 T
b00000000000000000000000011111111 U
b00000000000000000000000000000000 V
1W
b1100011 X
b00000000000000010100 Y
b00110 [
b10001 \
#66
0L
#67
b000 D
b000 E
1F
1H
b00000000000000000000000000010000 I
b000000000000 K
1L
b00000000000000000000000000000000 P
b00000000000000000000000000000000 Q
b00000000000000000000000000001100 S
b00000000000001011000010100010011 T
b00000000000000000000000000000000 U
b00000000000000000000000011111010 V
0W
b0010011 X
b00000000000000001100 Y
b00000 [
b01010 \
#68
0L
#69
b00000000000000000000000011111010 .
b00000000000000000000000000010100 I
b00000000000000000000000000010001 J
b000000000001 K
1L
b00000000000000000000000011111010 N
b00000000000000000000000000000001 Q
b00000000000000000000000000010000 S
b00000000000101011000010110010011 T
b00000000000000000000000000000001 U
b00000000000000000000000011111011 V
b00000000000000010000 Y
b00001 [
b01011 \
#70
0L
#71
b00000000000000000000000011111011 /
b111 D
b011 E
0F
0H
b00000000000000000000000000001100 I
b00000000000000000000000000001100 J
b111111111000 K
1L
b00000000000000000000000011111011 O
b00000000000000000000000011111111 P
b11111111111111111111111111111000 Q
b00000000000000000000000000010100 S
b11111110011001011001100011100011 T
b00000000000000000000000011111111 U
b00000000000000000000000000000000 V
1W
b1100011 X
b00000000000000010100 Y
b00110 [
b10001 \
#72
0L
#73
b000 D
b000 E
1F
1H
b00000000000000000000000000010000 I
b000000000000 K
1L
b00000000000000000000000000000000 P
b00000000000000000000000000000000 Q
b00000000000000000000000000001100 S
b00000000000001011000010100010011 T
b00000000000000000000000000000000 U
b00000000000000000000000011111011 V
0W
b0010011 X
b00000000000000001100 Y
b00000 [
b01010 \
#74
0L
#75
b00000000000000000000000011111011 .
b00000000000000000000000000010100 I
b00000000000000000000000000010001 J
b000000000001 K
1L
b00000000000000000000000011111011 N
b00000000000000000000000000000001 Q
b00000000000000000000000000010000 S
b00000000000101011000010110010011 T
b00000000000000000000000000000001 U
b00000000000000000000000011111100 V
b00000000000000010000 Y
b00001 [
b01011 \
#76
0L
#77
b00000000000000000000000011111100 /
b111 D
b011 E
0F
0H
b00000000000000000000000000001100 I
b00000000000000000000000000001100 J
b111111111000 K
1L
b00000000000000000000000011111100 O
b00000000000000000000000011111111 P
b11111111111111111111111111111000 Q
b00000000000000000000000000010100 S
b11111110011001011001100011100011 T
b00000000000000000000000011111111 U
b00000000000000000000000000000000 V
1W
b1100011 X
b00000000000000010100 Y
b00110 [
b10001 \
#78
0L
#79
b000 D
b000 E
1F
1H
b00000000000000000000000000010000 I
b000000000000 K
1L
b00000000000000000000000000000000 P
b00000000000000000000000000000000 Q
b00000000000000000000000000001100 S
b00000000000001011000010100010011 T
b00000000000000000000000000000000 U
b00000000000000000000000011111100 V
0W
b0010011 X
b00000000000000001100 Y
b00000 [
b01010 \
#80
0L
#81
b00000000000000000000000011111100 .
b00000000000000000000000000010100 I
b00000000000000000000000000010001 J
b000000000001 K
1L
b00000000000000000000000011111100 N
b00000000000000000000000000000001 Q
b00000000000000000000000000010000 S
b00000000000101011000010110010011 T
b00000000000000000000000000000001 U
b00000000000000000000000011111101 V
b00000000000000010000 Y
b00001 [
b01011 \
#82
0L
#83
b00000000000000000000000011111101 /
b111 D
b011 E
0F
0H
b00000000000000000000000000001100 I
b00000000000000000000000000001100 J
b111111111000 K
1L
b00000000000000000000000011111101 O
b00000000000000000000000011111111 P
b11111111111111111111111111111000 Q
b00000000000000000000000000010100 S
b11111110011001011001100011100011 T
b00000000000000000000000011111111 U
b00000000000000000000000000000000 V
1W
b1100011 X
b00000000000000010100 Y
b00110 [
b10001 \
#84
0L
#85
b000 D
b000 E
1F
1H
b00000000000000000000000000010000 I
b000000000000 K
1L
b00000000000000000000000000000000 P
b00000000000000000000000000000000 Q
b00000000000000000000000000001100 S
b00000000000001011000010100010011 T
b00000000000000000000000000000000 U
b00000000000000000000000011111101 V
0W
b0010011 X
b00000000000000001100 Y
b00000 [
b01010 \
#86
0L
#87
b00000000000000000000000011111101 .
b00000000000000000000000000010100 I
b00000000000000000000000000010001 J
b000000000001 K
1L
b00000000000000000000000011111101 N
b00000000000000000000000000000001 Q
b00000000000000000000000000010000 S
b00000000000101011000010110010011 T
b00000000000000000000000000000001 U
b00000000000000000000000011111110 V
b00000000000000010000 Y
b00001 [
b01011 \
#88
0L
#89
b00000000000000000000000011111110 /
b111 D
b011 E
0F
0H
b00000000000000000000000000001100 I
b00000000000000000000000000001100 J
b111111111000 K
1L
b00000000000000000000000011111110 O
b00000000000000000000000011111111 P
b11111111111111111111111111111000 Q
b00000000000000000000000000010100 S
b11111110011001011001100011100011 T
b00000000000000000000000011111111 U
b00000000000000000000000000000000 V
1W
b1100011 X
b00000000000000010100 Y
b00110 [
b10001 \
#90
0L
