RISC-V-Reduced/ram.sv
module ram #(
    parameter   A_WIDTH = 32,
                D_WIDTH = 8
)(
    input logic [A_WIDTH-1:0] address,
    input logic [2:0] bytes,
    input logic clk,
    input logic we,
    input logic [31:0] wd,
    output logic [31:0] dout
);

    logic [D_WIDTH-1:0] ram_array [200000:0];

    initial begin
        for (int i = 0; i < $size(ram_array); i++) begin
            ram_array[i] = 8'b0;
        end
    end 

    //read
    always_comb begin
        case (bytes)
            3'b000: dout = {{5'd24{ram_array[address][7]}}, {ram_array[address]}};//load byte   
            3'b001: dout = {{5'd16{ram_array[address + 1][7]}}, {ram_array[address + 1]}, {ram_array[address]}};//load half
            3'b010: dout = {{ram_array[address + 3]}, {ram_array[address + 2]}, {ram_array[address + 1]}, {ram_array[address]}};//load word
            3'b100: dout = {{24'b0}, {ram_array[7:0]}};//load byte uns
            3'b101: dout = {{16'b0}, {ram_array[address + 1]}, {ram_array[address]}};//load half uns
            default: begin
                dout = 32'b0;
            end
        endcase
    end

    //write
    always_ff @(posedge clk) begin
        // $display("[0]: ", ram_array[0], " [5]: ", ram_array[5], " [4]: ", ram_array[4], " [8]:", ram_array[8], " dout lb: ", dout , "\n");
        if (we) begin
            $display(ram_array[address])
            case (bytes)
                3'b000:ram_array[address] <= wd[7:0] ; //str byte
                
                3'b001: begin
                        ram_array[address] <= wd[7:0]; //str half
                        ram_array[address + 1] <= wd[15:8];
                    end

                3'b010: begin //str word
                        ram_array[address] <= wd[7:0];
                        ram_array[address + 1] <= wd[15:8];
                        ram_array[address + 2] <= wd[23:16];
                        ram_array[address + 3] <= wd[31:24];
                    end 
                default: begin
                    ram_array[address] <= ram_array[address];
                end
            endcase
        end
    end
    
endmodule

RISC-V-Reduced/rf.sv
module rf #(
    parameter  A_WIDTH = 5,
                D_WIDTH = 32
) (
    input logic clk,
    input logic we3,
    input logic [A_WIDTH-1:0] ad1,
    input logic [A_WIDTH-1:0] ad2,
    input logic [A_WIDTH-1:0] ad3,
    input logic [D_WIDTH-1:0] wd3,
    output logic [D_WIDTH-1:0] a0,
    output logic [D_WIDTH-1:0] rd1,
    output logic [D_WIDTH-1:0] rd2
);

    logic [D_WIDTH-1:0] rf_array [2**A_WIDTH-1:0];

    always_comb begin
        rd1 = rf_array[ad1];
        rd2 = rf_array[ad2];
    end

    initial begin
        for (int i = 0; i < $size(rf_array); i++) begin
            rf_array[i] = 32'h0000;
        end
    end

    assign a0 = rf_array[10];


    always_ff @(posedge clk) begin
        // $display("a0:", a0 , " a1: ", rf_array[11], " a2: ", rf_array[12], " din: ", wd3);
        if(we3) rf_array[ad3] <= wd3; 
    end
    
    
    
endmodule

RISC-V-Reduced/alu.sv
module alu #(
    parameter D_WIDTH = 32
)(
    input logic alusrc,
    input logic [2:0] aluctrl,
    input logic [D_WIDTH-1:0] aluop1,
    input logic [D_WIDTH-1:0] immop,
    input logic [D_WIDTH-1:0] regop2,
    output logic [D_WIDTH-1:0] aluout,
    output logic eq
);
    
    logic [D_WIDTH-1:0] aluop2;
    assign aluop2 = alusrc ? immop : regop2;
    always_comb begin
        
        case (aluctrl)
            3'b000: aluout = aluop1 + aluop2;
            3'b001: aluout = aluop1 - aluop2;
            3'b010: aluout = aluop1 & aluop2;
            3'b011: aluout = aluop1 | aluop2;
            3'b100: aluout = 32'b0;
            3'b101: aluout = 32'hffff; //slt
            3'b110: aluout = 32'b0;
            3'b111: aluout = 32'b0;
            default: aluout = 0;
        endcase
    end


    assign eq = (aluop1 == aluop2);

    
endmodule

RISC-V-Reduced/signextender.sv
module signextender(
    input logic [31:0] instruction,
    input logic [2:0] immsrc,
    output logic [31:0] immop
);
    
    always_comb begin
        case (immsrc)    
            3'b000: immop = {{5'd20{instruction[31]}}, instruction[31:20]}; // immediate
            3'b001: immop = {{5'd12{instruction[31]}}, instruction[31:12]}; // upper immediate
            3'b010: immop = {{5'd20{instruction[31]}}, instruction[31:25], instruction[11:7]}; // store
            3'b011: immop = {{5'd21{instruction[31]}}, instruction[7], instruction[30:25], instruction[11:8]}; // branch
            // 3'b100: immop = {instruction[31], instruction[19:12], instruction[20], instruction[30:21]}; // jump
            default: immop = 32'b0;
        endcase
    end
    
endmodule

RISC-V-Reduced/instrmem.sv
module instrmem #(
    parameter   A_WIDTH = 32,
                D_WIDTH = 8        
) (
    input [A_WIDTH-1:0] address,
    output [31:0] dout
);
    logic [D_WIDTH-1:0] rom_array [2000:0];
    
    initial begin 
        $display("Loading rom.");
        $readmemh("counter.hex", rom_array);
        $display("Program written to ROM successfully");
    end;

    assign dout = {{rom_array[address]}, {rom_array[address+1]}, {rom_array[address+2]}, {rom_array[address+3]}}; 

endmodule

omar/RISC-V-1/temp completed/pcountunit.sv

module pcountunit #(
    parameter WIDTH = 32
) (
    input logic pcsrc,
    input logic clk,
    input logic rst,
    input logic [WIDTH-1:0] immop,
    output logic [WIDTH-1:0] pc
);

    logic [WIDTH-1:0] next_pc;
    logic [WIDTH-1:0] branch_pc;
    
    always_comb begin
        branch_pc = pc + immop;
        next_pc = pcsrc ? branch_pc : pc + 4;    
    end

    always_ff @(posedge clk) begin
        if(rst) pc <= 32'b0;
        else pc <= next_pc;
    end



endmodule

RISC-V-Reduced/controlunit.sv
module controlunit(
    input logic [31:0] instruction,
    input logic eq,
    output logic regwrite,
    output logic [2:0] aluctrl,
    output logic alusrc,
    output logic pcsrc,
    output logic [2:0] immsrc,
    output logic memwrite,
    output logic [2:0] addrmode,
    output logic resultsrc
);
    logic [6:0] opcode;
    logic [2:0] funct3;
    logic [31:25] funct7;
    logic [1:0] aluop;

    always_comb begin
        funct3 = instruction[14:12];
        opcode = instruction[6:0];
        aluctrl = 3'b000;
        case (opcode)
            7'd51: begin //register-register ops
                funct7 = instruction[31:25];            
                regwrite = 1'b1;
                immsrc = 3'b111;
                alusrc = 1'b0;
                memwrite = 1'b0;
                resultsrc = 1'b0;
                pcsrc = 1'b0;
                aluop = 2'b10;
            end

            7'd3: begin //load ops
                regwrite = 1'b1;
                immsrc = 3'b000;
                alusrc = 1'b1;
                memwrite = 1'b0;
                resultsrc = 1'b1;
                pcsrc = 1'b0;
                aluop = 2'b00;
                addrmode = funct3;
            end
            
            7'd19: begin //alu imm ops
                regwrite = 1'b1;
                alusrc = 1'b1;
                aluop = 2'b11;
                immsrc = 3'b000;
                pcsrc = 1'b0;
                memwrite = 1'b0;
                resultsrc = 1'b0;
            end 
            
            7'd35: begin //str ops
                regwrite = 1'b0;
                immsrc = 3'b010;
                alusrc = 1'b1;
                memwrite = 1'b1;
                pcsrc = 1'b0;  
                aluop = 00; 
                addrmode = funct3;      
            end
            
            7'd99: begin //branch ops
                aluop = 01;
                regwrite = 1'b0;
                immsrc = 3'b011;
                alusrc = 1'b0;
                memwrite = 1'b0;
                case(funct3)
                    3'b000: pcsrc = eq;
                    3'b001: pcsrc = !eq;
                    // 3'b010:
                    // 3'b011:
                    // 3'b100:
                    // 3'b101:
                    // 3'b110:
                    // 3'b111:
                    default: pcsrc = 1'b0;
                endcase

            end
            // 7'd23:
            // 7'd55:
            // 7'd103:
            // 7'd111:
            default: begin
                funct3 = 3'b0;
                funct7 = 7'b0;
                pcsrc = 1'b0;
                regwrite = 1'b0;
                alusrc = 1'b1;
                immsrc = 3'b111;
                memwrite = 1'b0;
            end
        endcase
    end

    always_comb begin
        case (aluop)
            
            2'b00: aluctrl = 3'b000; // load/ str
            2'b01: aluctrl = 3'b111; //branch
            2'b10: begin // register - register
                case (funct3)
                    3'b000: aluctrl = opcode[5] & funct7[5] ? 3'b001 : 3'b000; // add or sub  
                    // 3'b001: 
                    3'b010: aluctrl = 3'b101; //slt
                    // 3'b011: 
                    // 3'b100:
                    // 3'b101:
                    3'b110: aluctrl = 3'b011; //or
                    3'b111: aluctrl = 3'b010; //and
                    default aluctrl = 3'b000;
                endcase
            end
            default: begin // will automatically set aluctrl to funct 3 (assuming that any other instruction is immediate), this may need to change when U and J are implemented
                aluctrl = funct3;
            end
        endcase
    end
    
endmodule

RISC-V-Reduced/cpu.sv
module cpu #(
    parameter WIDTH = 32
) (
    input logic clk, 
    input logic rst,
    output logic [WIDTH-1:0] a0_output,
    output logic [WIDTH-1:0] rf_dout1,
    output logic [WIDTH-1:0] rf_dout2,
    output logic [WIDTH-1:0] interm_immop,
    output logic [4:0] rd_add,
    output logic [WIDTH-1:0] prog_addr,
    output logic [WIDTH-1:0] interm_ins,
    output logic [WIDTH-1:0] rout_test
    
);

logic [WIDTH-1:0] interm_aluout;
logic [2:0] interm_aluctrl;
logic [2:0] interm_immsrc;
logic interm_alusrc;
logic interm_eq;
logic interm_pcsrc;
logic write_en;
logic [2:0] inter_addrmode;
logic interm_memwrite;
logic interm_resultsrc;
logic [WIDTH-1:0] result = interm_resultsrc ? rout_test : interm_aluout;

assign rd_add = interm_ins[19:15];

controlunit ctrlunit(
    .instruction(interm_ins), //in
    .eq(interm_eq), //in
    .regwrite(write_en), //out
    .aluctrl(interm_aluctrl), //out
    .alusrc(interm_alusrc), //out
    .pcsrc(interm_pcsrc), //out
    .immsrc(interm_immsrc), //out
    .memwrite(interm_memwrite), //out
    .addrmode(inter_addrmode), //out
    .resultsrc(interm_resultsrc) //out
);

pcountunit programcounter(
    .clk(clk), //in
    .rst(rst), //in
    .pcsrc(interm_pcsrc), //in
    .immop(interm_immop), //in
    .pc(prog_addr) //out
);

instrmem programmem(
    .address(prog_addr),
    .dout(interm_ins)
);

signextender sgnextend(
    .instruction(interm_ins),
    .immsrc(interm_immsrc),
    .immop(interm_immop)
);


alu alu(
    .alusrc(interm_alusrc),
    .aluctrl(interm_aluctrl),
    .aluop1(rf_dout1),
    .immop(interm_immop),
    .regop2(rf_dout2),
    .aluout(interm_aluout),
    .eq(interm_eq)
);

rf registerfile(
    .clk(clk), //in
    .we3(write_en), //in
    .ad1(interm_ins[19:15]), //in
    .ad2(interm_ins[24:20]), //in
    .ad3(interm_ins[11:7]), //in
    .wd3(result), //in
    .a0(a0_output), //out
    .rd1(rf_dout1), //out
    .rd2(rf_dout2) //out
);

ram ram(
    .clk(clk),
    .address(interm_aluout),
    .bytes(inter_addrmode),
    .we(interm_memwrite),
    .wd(rf_dout2),
    .dout(rout_test)
);



endmodule

RISC-V-Reduced/cpu.vcd
$version Generated by VerilatedVcd $end
$date Wed Nov 30 13:02:00 2022 $end
$timescale 1ps $end

 $scope module TOP $end
  $var wire 32 X a0_output [31:0] $end
  $var wire  1 V clk $end
  $var wire 32 [ interm_immop [31:0] $end
  $var wire 32 ^ interm_ins [31:0] $end
  $var wire 32 ] prog_addr [31:0] $end
  $var wire  5 \ rd_add [4:0] $end
  $var wire 32 Y rf_dout1 [31:0] $end
  $var wire 32 Z rf_dout2 [31:0] $end
  $var wire 32 _ rout_test [31:0] $end
  $var wire  1 W rst $end
  $scope module cpu $end
   $var wire 32 d WIDTH [31:0] $end
   $var wire 32 X a0_output [31:0] $end
   $var wire  1 V clk $end
   $var wire  3 L inter_addrmode [2:0] $end
   $var wire  3 F interm_aluctrl [2:0] $end
   $var wire 32 E interm_aluout [31:0] $end
   $var wire  1 H interm_alusrc $end
   $var wire  1 I interm_eq $end
   $var wire 32 [ interm_immop [31:0] $end
   $var wire  3 G interm_immsrc [2:0] $end
   $var wire 32 ^ interm_ins [31:0] $end
   $var wire  1 M interm_memwrite $end
   $var wire  1 J interm_pcsrc $end
   $var wire  1 N interm_resultsrc $end
   $var wire 32 ] prog_addr [31:0] $end
   $var wire  5 \ rd_add [4:0] $end
   $var wire 32 ` result [31:0] $end
   $var wire 32 Y rf_dout1 [31:0] $end
   $var wire 32 Z rf_dout2 [31:0] $end
   $var wire 32 _ rout_test [31:0] $end
   $var wire  1 W rst $end
   $var wire  1 K write_en $end
   $scope module alu $end
    $var wire 32 d D_WIDTH [31:0] $end
    $var wire  3 F aluctrl [2:0] $end
    $var wire 32 Y aluop1 [31:0] $end
    $var wire 32 O aluop2 [31:0] $end
    $var wire 32 E aluout [31:0] $end
    $var wire  1 H alusrc $end
    $var wire  1 I eq $end
    $var wire 32 [ immop [31:0] $end
    $var wire 32 Z regop2 [31:0] $end
   $upscope $end
   $scope module ctrlunit $end
    $var wire  3 L addrmode [2:0] $end
    $var wire  3 F aluctrl [2:0] $end
    $var wire  2 S aluop [1:0] $end
    $var wire  1 H alusrc $end
    $var wire  1 I eq $end
    $var wire  3 Q funct3 [2:0] $end
    $var wire  7 R funct7 [31:25] $end
    $var wire  3 G immsrc [2:0] $end
    $var wire 32 ^ instruction [31:0] $end
    $var wire  1 M memwrite $end
    $var wire  7 P opcode [6:0] $end
    $var wire  1 J pcsrc $end
    $var wire  1 K regwrite $end
    $var wire  1 N resultsrc $end
   $upscope $end
   $scope module programcounter $end
    $var wire 32 d WIDTH [31:0] $end
    $var wire 32 U branch_pc [31:0] $end
    $var wire  1 V clk $end
    $var wire 32 [ immop [31:0] $end
    $var wire 32 T next_pc [31:0] $end
    $var wire 32 ] pc [31:0] $end
    $var wire  1 J pcsrc $end
    $var wire  1 W rst $end
   $upscope $end
   $scope module programmem $end
    $var wire 32 d A_WIDTH [31:0] $end
    $var wire 32 e D_WIDTH [31:0] $end
    $var wire 32 ] address [31:0] $end
    $var wire 32 ^ dout [31:0] $end
   $upscope $end
   $scope module ram $end
    $var wire 32 d A_WIDTH [31:0] $end
    $var wire 32 e D_WIDTH [31:0] $end
    $var wire 32 E address [31:0] $end
    $var wire  3 L bytes [2:0] $end
    $var wire  1 V clk $end
    $var wire 32 _ dout [31:0] $end
    $var wire 32 Z wd [31:0] $end
    $var wire  1 M we $end
    $scope module unnamedblk1 $end
     $var wire 32 # i [31:0] $end
    $upscope $end
   $upscope $end
   $scope module registerfile $end
    $var wire 32 f A_WIDTH [31:0] $end
    $var wire 32 d D_WIDTH [31:0] $end
    $var wire 32 X a0 [31:0] $end
    $var wire  5 a ad1 [4:0] $end
    $var wire  5 b ad2 [4:0] $end
    $var wire  5 c ad3 [4:0] $end
    $var wire  1 V clk $end
    $var wire 32 Y rd1 [31:0] $end
    $var wire 32 Z rd2 [31:0] $end
    $var wire 32 % rf_array[0] [31:0] $end
    $var wire 32 / rf_array[10] [31:0] $end
    $var wire 32 0 rf_array[11] [31:0] $end
    $var wire 32 1 rf_array[12] [31:0] $end
    $var wire 32 2 rf_array[13] [31:0] $end
    $var wire 32 3 rf_array[14] [31:0] $end
    $var wire 32 4 rf_array[15] [31:0] $end
    $var wire 32 5 rf_array[16] [31:0] $end
    $var wire 32 6 rf_array[17] [31:0] $end
    $var wire 32 7 rf_array[18] [31:0] $end
    $var wire 32 8 rf_array[19] [31:0] $end
    $var wire 32 & rf_array[1] [31:0] $end
    $var wire 32 9 rf_array[20] [31:0] $end
    $var wire 32 : rf_array[21] [31:0] $end
    $var wire 32 ; rf_array[22] [31:0] $end
    $var wire 32 < rf_array[23] [31:0] $end
    $var wire 32 = rf_array[24] [31:0] $end
    $var wire 32 > rf_array[25] [31:0] $end
    $var wire 32 ? rf_array[26] [31:0] $end
    $var wire 32 @ rf_array[27] [31:0] $end
    $var wire 32 A rf_array[28] [31:0] $end
    $var wire 32 B rf_array[29] [31:0] $end
    $var wire 32 ' rf_array[2] [31:0] $end
    $var wire 32 C rf_array[30] [31:0] $end
    $var wire 32 D rf_array[31] [31:0] $end
    $var wire 32 ( rf_array[3] [31:0] $end
    $var wire 32 ) rf_array[4] [31:0] $end
    $var wire 32 * rf_array[5] [31:0] $end
    $var wire 32 + rf_array[6] [31:0] $end
    $var wire 32 , rf_array[7] [31:0] $end
    $var wire 32 - rf_array[8] [31:0] $end
    $var wire 32 . rf_array[9] [31:0] $end
    $var wire 32 ` wd3 [31:0] $end
    $var wire  1 K we3 $end
    $scope module unnamedblk1 $end
     $var wire 32 $ i [31:0] $end
    $upscope $end
   $upscope $end
   $scope module sgnextend $end
    $var wire 32 [ immop [31:0] $end
    $var wire  3 G immsrc [2:0] $end
    $var wire 32 ^ instruction [31:0] $end
   $upscope $end
  $upscope $end
 $upscope $end
$enddefinitions $end


#0
b00000000000000000000000000000000 #
b00000000000000000000000000000000 $
b00000000000000000000000000000000 %
b00000000000000000000000000000000 &
b00000000000000000000000000000000 '
b00000000000000000000000000000000 (
b00000000000000000000000000000000 )
b00000000000000000000000000000000 *
b00000000000000000000000000000000 +
b00000000000000000000000000000000 ,
b00000000000000000000000000000000 -
b00000000000000000000000000000000 .
b00000000000000000000000000000000 /
b00000000000000000000000000000000 0
b00000000000000000000000000000000 1
b00000000000000000000000000000000 2
b00000000000000000000000000000000 3
b00000000000000000000000000000000 4
b00000000000000000000000000000000 5
b00000000000000000000000000000000 6
b00000000000000000000000000000000 7
b00000000000000000000000000000000 8
b00000000000000000000000000000000 9
b00000000000000000000000000000000 :
b00000000000000000000000000000000 ;
b00000000000000000000000000000000 <
b00000000000000000000000000000000 =
b00000000000000000000000000000000 >
b00000000000000000000000000000000 ?
b00000000000000000000000000000000 @
b00000000000000000000000000000000 A
b00000000000000000000000000000000 B
b00000000000000000000000000000000 C
b00000000000000000000000000000000 D
b00000000000000000000000000000000 E
b000 F
b000 G
0H
0I
0J
0K
b000 L
0M
0N
b00000000000000000000000000000000 O
b0000000 P
b000 Q
b0000000 R
b00 S
b00000000000000000000000000000000 T
b00000000000000000000000000000000 U
0V
0W
b00000000000000000000000000000000 X
b00000000000000000000000000000000 Y
b00000000000000000000000000000000 Z
b00000000000000000000000000000000 [
b00000 \
b00000000000000000000000000000000 ]
b00000000000000000000000000000000 ^
b00000000000000000000000000000000 _
b00000000000000000000000000000000 `
b00000 a
b00000 b
b00000 c
b00000000000000000000000000100000 d
b00000000000000000000000000001000 e
b00000000000000000000000000000101 f
#1
b00000000000000110000110101000001 #
b00000000000000000000000000100000 $
b00000000000000000000000011111111 E
1H
1K
b00000000000000000000000011111111 O
b0010011 P
b11 S
b00000000000000000000000000000100 T
b00000000000000000000000011111111 U
1V
b00000000000000000000000011111111 [
b00001111111100000000001100010011 ^
b00000000000000000000000011111111 `
b11111 b
b00110 c
#2
0V
#3
b00000000000000000000000011111111 +
b00000000000000000000000000000000 E
1I
b00000000000000000000000000000000 O
b00000000000000000000000000001000 T
b00000000000000000000000000000100 U
1V
b00000000000000000000000000000000 [
b00000000000000000000000000000100 ]
b00000000000000000000010100010011 ^
b00000000000000000000000000000000 `
b00000 b
b01010 c
#4
0V
#5
b00000000000000000000000011110000 E
0I
b00000000000000000000000011110000 O
b00000000000000000000000000001100 T
b00000000000000000000000011111000 U
1V
b00000000000000000000000011110000 [
b00000000000000000000000000001000 ]
b00001111000000000000010110010011 ^
b00000000000000000000000011110000 `
b10000 b
b01011 c
#6
0V
#7
b00000000000000000000000011110000 0
b00000000000000000000000000000000 O
b00000000000000000000000000010000 T
b00000000000000000000000000001100 U
1V
b00000000000000000000000011110000 Y
b00000000000000000000000000000000 [
b01011 \
b00000000000000000000000000001100 ]
b00000000000001011000010100010011 ^
b01011 a
b00000 b
b01010 c
#8
0V
#9
b00000000000000000000000011110000 /
b00000000000000000000000011110001 E
b00000000000000000000000000000001 O
b00000000000000000000000000010100 T
b00000000000000000000000000010001 U
1V
b00000000000000000000000011110000 X
b00000000000000000000000000000001 [
b00000000000000000000000000010000 ]
b00000000000101011000010110010011 ^
b00000000000000000000000011110001 `
b00001 b
b01011 c
#10
0V
#11
b00000000000000000000000011110001 0
b00000000000000000000000000000000 E
b111 F
b011 G
0H
1J
0K
b00000000000000000000000011111111 O
b1100011 P
b001 Q
b01 S
b00000000000000000000000000001100 T
b00000000000000000000000000001100 U
1V
b00000000000000000000000011110001 Y
b00000000000000000000000011111111 Z
b11111111111111111111111111111000 [
b00000000000000000000000000010100 ]
b11111110011001011001100011100011 ^
b00000000000000000000000000000000 `
b00110 b
b10001 c
#12
0V
#13
b00000000000000000000000011110001 E
b000 F
b000 G
1H
0J
1K
b00000000000000000000000000000000 O
b0010011 P
b000 Q
b11 S
b00000000000000000000000000010000 T
1V
b00000000000000000000000000000000 Z
b00000000000000000000000000000000 [
b00000000000000000000000000001100 ]
b00000000000001011000010100010011 ^
b00000000000000000000000011110001 `
b00000 b
b01010 c
#14
0V
#15
b00000000000000000000000011110001 /
b00000000000000000000000011110010 E
b00000000000000000000000000000001 O
b00000000000000000000000000010100 T
b00000000000000000000000000010001 U
1V
b00000000000000000000000011110001 X
b00000000000000000000000000000001 [
b00000000000000000000000000010000 ]
b00000000000101011000010110010011 ^
b00000000000000000000000011110010 `
b00001 b
b01011 c
#16
0V
#17
b00000000000000000000000011110010 0
b00000000000000000000000000000000 E
b111 F
b011 G
0H
1J
0K
b00000000000000000000000011111111 O
b1100011 P
b001 Q
b01 S
b00000000000000000000000000001100 T
b00000000000000000000000000001100 U
1V
b00000000000000000000000011110010 Y
b00000000000000000000000011111111 Z
b11111111111111111111111111111000 [
b00000000000000000000000000010100 ]
b11111110011001011001100011100011 ^
b00000000000000000000000000000000 `
b00110 b
b10001 c
#18
0V
#19
b00000000000000000000000011110010 E
b000 F
b000 G
1H
0J
1K
b00000000000000000000000000000000 O
b0010011 P
b000 Q
b11 S
b00000000000000000000000000010000 T
1V
b00000000000000000000000000000000 Z
b00000000000000000000000000000000 [
b00000000000000000000000000001100 ]
b00000000000001011000010100010011 ^
b00000000000000000000000011110010 `
b00000 b
b01010 c
#20
0V
#21
b00000000000000000000000011110010 /
b00000000000000000000000011110011 E
b00000000000000000000000000000001 O
b00000000000000000000000000010100 T
b00000000000000000000000000010001 U
1V
b00000000000000000000000011110010 X
b00000000000000000000000000000001 [
b00000000000000000000000000010000 ]
b00000000000101011000010110010011 ^
b00000000000000000000000011110011 `
b00001 b
b01011 c
#22
0V
#23
b00000000000000000000000011110011 0
b00000000000000000000000000000000 E
b111 F
b011 G
0H
1J
0K
b00000000000000000000000011111111 O
b1100011 P
b001 Q
b01 S
b00000000000000000000000000001100 T
b00000000000000000000000000001100 U
1V
b00000000000000000000000011110011 Y
b00000000000000000000000011111111 Z
b11111111111111111111111111111000 [
b00000000000000000000000000010100 ]
b11111110011001011001100011100011 ^
b00000000000000000000000000000000 `
b00110 b
b10001 c
#24
0V
#25
b00000000000000000000000011110011 E
b000 F
b000 G
1H
0J
1K
b00000000000000000000000000000000 O
b0010011 P
b000 Q
b11 S
b00000000000000000000000000010000 T
1V
b00000000000000000000000000000000 Z
b00000000000000000000000000000000 [
b00000000000000000000000000001100 ]
b00000000000001011000010100010011 ^
b00000000000000000000000011110011 `
b00000 b
b01010 c
#26
0V
#27
b00000000000000000000000011110011 /
b00000000000000000000000011110100 E
b00000000000000000000000000000001 O
b00000000000000000000000000010100 T
b00000000000000000000000000010001 U
1V
b00000000000000000000000011110011 X
b00000000000000000000000000000001 [
b00000000000000000000000000010000 ]
b00000000000101011000010110010011 ^
b00000000000000000000000011110100 `
b00001 b
b01011 c
#28
0V
#29
b00000000000000000000000011110100 0
b00000000000000000000000000000000 E
b111 F
b011 G
0H
1J
0K
b00000000000000000000000011111111 O
b1100011 P
b001 Q
b01 S
b00000000000000000000000000001100 T
b00000000000000000000000000001100 U
1V
b00000000000000000000000011110100 Y
b00000000000000000000000011111111 Z
b11111111111111111111111111111000 [
b00000000000000000000000000010100 ]
b11111110011001011001100011100011 ^
b00000000000000000000000000000000 `
b00110 b
b10001 c
#30
0V
#31
b00000000000000000000000011110100 E
b000 F
b000 G
1H
0J
1K
b00000000000000000000000000000000 O
b0010011 P
b000 Q
b11 S
b00000000000000000000000000010000 T
1V
b00000000000000000000000000000000 Z
b00000000000000000000000000000000 [
b00000000000000000000000000001100 ]
b00000000000001011000010100010011 ^
b00000000000000000000000011110100 `
b00000 b
b01010 c
#32
0V
#33
b00000000000000000000000011110100 /
b00000000000000000000000011110101 E
b00000000000000000000000000000001 O
b00000000000000000000000000010100 T
b00000000000000000000000000010001 U
1V
b00000000000000000000000011110100 X
b00000000000000000000000000000001 [
b00000000000000000000000000010000 ]
b00000000000101011000010110010011 ^
b00000000000000000000000011110101 `
b00001 b
b01011 c
#34
0V
#35
b00000000000000000000000011110101 0
b00000000000000000000000000000000 E
b111 F
b011 G
0H
1J
0K
b00000000000000000000000011111111 O
b1100011 P
b001 Q
b01 S
b00000000000000000000000000001100 T
b00000000000000000000000000001100 U
1V
b00000000000000000000000011110101 Y
b00000000000000000000000011111111 Z
b11111111111111111111111111111000 [
b00000000000000000000000000010100 ]
b11111110011001011001100011100011 ^
b00000000000000000000000000000000 `
b00110 b
b10001 c
#36
0V
#37
b00000000000000000000000011110101 E
b000 F
b000 G
1H
0J
1K
b00000000000000000000000000000000 O
b0010011 P
b000 Q
b11 S
b00000000000000000000000000010000 T
1V
b00000000000000000000000000000000 Z
b00000000000000000000000000000000 [
b00000000000000000000000000001100 ]
b00000000000001011000010100010011 ^
b00000000000000000000000011110101 `
b00000 b
b01010 c
#38
0V
#39
b00000000000000000000000011110101 /
b00000000000000000000000011110110 E
b00000000000000000000000000000001 O
b00000000000000000000000000010100 T
b00000000000000000000000000010001 U
1V
b00000000000000000000000011110101 X
b00000000000000000000000000000001 [
b00000000000000000000000000010000 ]
b00000000000101011000010110010011 ^
b00000000000000000000000011110110 `
b00001 b
b01011 c
#40
0V
#41
b00000000000000000000000011110110 0
b00000000000000000000000000000000 E
b111 F
b011 G
0H
1J
0K
b00000000000000000000000011111111 O
b1100011 P
b001 Q
b01 S
b00000000000000000000000000001100 T
b00000000000000000000000000001100 U
1V
b00000000000000000000000011110110 Y
b00000000000000000000000011111111 Z
b11111111111111111111111111111000 [
b00000000000000000000000000010100 ]
b11111110011001011001100011100011 ^
b00000000000000000000000000000000 `
b00110 b
b10001 c
#42
0V
#43
b00000000000000000000000011110110 E
b000 F
b000 G
1H
0J
1K
b00000000000000000000000000000000 O
b0010011 P
b000 Q
b11 S
b00000000000000000000000000010000 T
1V
b00000000000000000000000000000000 Z
b00000000000000000000000000000000 [
b00000000000000000000000000001100 ]
b00000000000001011000010100010011 ^
b00000000000000000000000011110110 `
b00000 b
b01010 c
#44
0V
#45
b00000000000000000000000011110110 /
b00000000000000000000000011110111 E
b00000000000000000000000000000001 O
b00000000000000000000000000010100 T
b00000000000000000000000000010001 U
1V
b00000000000000000000000011110110 X
b00000000000000000000000000000001 [
b00000000000000000000000000010000 ]
b00000000000101011000010110010011 ^
b00000000000000000000000011110111 `
b00001 b
b01011 c
#46
0V
#47
b00000000000000000000000011110111 0
b00000000000000000000000000000000 E
b111 F
b011 G
0H
1J
0K
b00000000000000000000000011111111 O
b1100011 P
b001 Q
b01 S
b00000000000000000000000000001100 T
b00000000000000000000000000001100 U
1V
b00000000000000000000000011110111 Y
b00000000000000000000000011111111 Z
b11111111111111111111111111111000 [
b00000000000000000000000000010100 ]
b11111110011001011001100011100011 ^
b00000000000000000000000000000000 `
b00110 b
b10001 c
#48
0V
#49
b00000000000000000000000011110111 E
b000 F
b000 G
1H
0J
1K
b00000000000000000000000000000000 O
b0010011 P
b000 Q
b11 S
b00000000000000000000000000010000 T
1V
b00000000000000000000000000000000 Z
b00000000000000000000000000000000 [
b00000000000000000000000000001100 ]
b00000000000001011000010100010011 ^
b00000000000000000000000011110111 `
b00000 b
b01010 c
#50
0V
#51
b00000000000000000000000011110111 /
b00000000000000000000000011111000 E
b00000000000000000000000000000001 O
b00000000000000000000000000010100 T
b00000000000000000000000000010001 U
1V
b00000000000000000000000011110111 X
b00000000000000000000000000000001 [
b00000000000000000000000000010000 ]
b00000000000101011000010110010011 ^
b00000000000000000000000011111000 `
b00001 b
b01011 c
#52
0V
#53
b00000000000000000000000011111000 0
b00000000000000000000000000000000 E
b111 F
b011 G
0H
1J
0K
b00000000000000000000000011111111 O
b1100011 P
b001 Q
b01 S
b00000000000000000000000000001100 T
b00000000000000000000000000001100 U
1V
b00000000000000000000000011111000 Y
b00000000000000000000000011111111 Z
b11111111111111111111111111111000 [
b00000000000000000000000000010100 ]
b11111110011001011001100011100011 ^
b00000000000000000000000000000000 `
b00110 b
b10001 c
#54
0V
#55
b00000000000000000000000011111000 E
b000 F
b000 G
1H
0J
1K
b00000000000000000000000000000000 O
b0010011 P
b000 Q
b11 S
b00000000000000000000000000010000 T
1V
b00000000000000000000000000000000 Z
b00000000000000000000000000000000 [
b00000000000000000000000000001100 ]
b00000000000001011000010100010011 ^
b00000000000000000000000011111000 `
b00000 b
b01010 c
#56
0V
#57
b00000000000000000000000011111000 /
b00000000000000000000000011111001 E
b00000000000000000000000000000001 O
b00000000000000000000000000010100 T
b00000000000000000000000000010001 U
1V
b00000000000000000000000011111000 X
b00000000000000000000000000000001 [
b00000000000000000000000000010000 ]
b00000000000101011000010110010011 ^
b00000000000000000000000011111001 `
b00001 b
b01011 c
#58
0V
#59
b00000000000000000000000011111001 0
b00000000000000000000000000000000 E
b111 F
b011 G
0H
1J
0K
b00000000000000000000000011111111 O
b1100011 P
b001 Q
b01 S
b00000000000000000000000000001100 T
b00000000000000000000000000001100 U
1V
b00000000000000000000000011111001 Y
b00000000000000000000000011111111 Z
b11111111111111111111111111111000 [
b00000000000000000000000000010100 ]
b11111110011001011001100011100011 ^
b00000000000000000000000000000000 `
b00110 b
b10001 c
#60
0V
#61
b00000000000000000000000011111001 E
b000 F
b000 G
1H
0J
1K
b00000000000000000000000000000000 O
b0010011 P
b000 Q
b11 S
b00000000000000000000000000010000 T
1V
b00000000000000000000000000000000 Z
b00000000000000000000000000000000 [
b00000000000000000000000000001100 ]
b00000000000001011000010100010011 ^
b00000000000000000000000011111001 `
b00000 b
b01010 c
#62
0V
